{
  "$schema": "http://json-schema.org/draft-07/schema",
  "uris": {
    "type": "string",
    "format": "uri",
    "enum": [
      "http://qudt.org/vocab/unit/MicroW-PER-M2",
      "http://qudt.org/vocab/unit/PER-H",
      "http://qudt.org/vocab/unit/DEG_C2-PER-SEC",
      "http://qudt.org/vocab/unit/FT3-PER-MIN-FT2",
      "http://qudt.org/vocab/unit/SouthAfricanRand",
      "http://qudt.org/vocab/unit/LB_F-PER-FT",
      "http://qudt.org/vocab/unit/NanoH",
      "http://qudt.org/vocab/unit/FA",
      "http://qudt.org/vocab/unit/EV-SEC",
      "http://qudt.org/vocab/unit/MilliM_H2O",
      "http://qudt.org/vocab/unit/PER-DAY",
      "http://qudt.org/vocab/unit/MilliBQ-PER-GM",
      "http://qudt.org/vocab/unit/TON_Metric-PER-DAY",
      "http://qudt.org/vocab/unit/MI_N-PER-MIN",
      "http://qudt.org/vocab/unit/BDT",
      "http://qudt.org/vocab/unit/DeciM2",
      "http://qudt.org/vocab/unit/Lempira",
      "http://qudt.org/vocab/unit/Leone",
      "http://qudt.org/vocab/unit/ElementaryCharge",
      "http://qudt.org/vocab/unit/C_Stat-PER-CentiM2",
      "http://qudt.org/vocab/unit/STR",
      "http://qudt.org/vocab/unit/HZ",
      "http://qudt.org/vocab/unit/DeciTON_Metric",
      "http://qudt.org/vocab/unit/LB-IN2",
      "http://qudt.org/vocab/unit/MilliS-PER-CentiM",
      "http://qudt.org/vocab/unit/N",
      "http://qudt.org/vocab/unit/PER-PSI",
      "http://qudt.org/vocab/unit/HectoGM",
      "http://qudt.org/vocab/unit/Riel",
      "http://qudt.org/vocab/unit/BTU_IT-PER-DEG_R",
      "http://qudt.org/vocab/unit/GigaBYTE",
      "http://qudt.org/vocab/unit/FR",
      "http://qudt.org/vocab/unit/DEG_C-PER-HR",
      "http://qudt.org/vocab/unit/BrazilianReal",
      "http://qudt.org/vocab/unit/N-M2-PER-A",
      "http://qudt.org/vocab/unit/PakistanRupee",
      "http://qudt.org/vocab/unit/REV-PER-MIN",
      "http://qudt.org/vocab/unit/MegaGM",
      "http://qudt.org/vocab/unit/TON_FG",
      "http://qudt.org/vocab/unit/MilliGM-PER-DAY",
      "http://qudt.org/vocab/unit/MicroGM-PER-M2-DAY",
      "http://qudt.org/vocab/unit/USDollar-SameDay",
      "http://qudt.org/vocab/unit/BTU_TH-PER-HR",
      "http://qudt.org/vocab/unit/C-PER-CentiM2",
      "http://qudt.org/vocab/unit/PicoMOL-PER-M-W-SEC",
      "http://qudt.org/vocab/unit/HectoPA-L-PER-SEC",
      "http://qudt.org/vocab/unit/J-PER-KiloGM-K",
      "http://qudt.org/vocab/unit/M2-PER-MOL",
      "http://qudt.org/vocab/unit/UnitPole",
      "http://qudt.org/vocab/unit/BBL_UK_PET-PER-SEC",
      "http://qudt.org/vocab/unit/DEGREE_BALLING",
      "http://qudt.org/vocab/unit/MilliM-PER-HR",
      "http://qudt.org/vocab/unit/MilliGM",
      "http://qudt.org/vocab/unit/OZ-PER-DAY",
      "http://qudt.org/vocab/unit/LM-PER-W",
      "http://qudt.org/vocab/unit/N-PER-A",
      "http://qudt.org/vocab/unit/MilliC-PER-M3",
      "http://qudt.org/vocab/unit/DeciM3-PER-SEC",
      "http://qudt.org/vocab/unit/MilliMOL-PER-M3-DAY",
      "http://qudt.org/vocab/unit/WIREuro",
      "http://qudt.org/vocab/unit/IU-PER-L",
      "http://qudt.org/vocab/unit/IcelandKrona",
      "http://qudt.org/vocab/unit/NorthKoreanWon",
      "http://qudt.org/vocab/unit/MilliM-PER-YR",
      "http://qudt.org/vocab/unit/PK_UK",
      "http://qudt.org/vocab/unit/MicroS-PER-CentiM",
      "http://qudt.org/vocab/unit/BTU_IT-PER-LB_F-DEG_R",
      "http://qudt.org/vocab/unit/PK_UK-PER-SEC",
      "http://qudt.org/vocab/unit/MilliGM-PER-M2-SEC",
      "http://qudt.org/vocab/unit/DecaPA",
      "http://qudt.org/vocab/unit/TON_UK",
      "http://qudt.org/vocab/unit/PARSEC",
      "http://qudt.org/vocab/unit/KiloLB_F-PER-FT",
      "http://qudt.org/vocab/unit/M2-PER-J",
      "http://qudt.org/vocab/unit/CUP",
      "http://qudt.org/vocab/unit/KiloCAL_TH",
      "http://qudt.org/vocab/unit/SpecialDrawingRights",
      "http://qudt.org/vocab/unit/HART",
      "http://qudt.org/vocab/unit/HectoPA-PER-HR",
      "http://qudt.org/vocab/unit/BAR-M3-PER-SEC",
      "http://qudt.org/vocab/unit/M2-HZ4",
      "http://qudt.org/vocab/unit/J-PER-M2",
      "http://qudt.org/vocab/unit/MicroA",
      "http://qudt.org/vocab/unit/MilliSV",
      "http://qudt.org/vocab/unit/FemtoMOL-PER-L",
      "http://qudt.org/vocab/unit/MilliBQ-PER-L",
      "http://qudt.org/vocab/unit/MilliGAL-PER-MO",
      "http://qudt.org/vocab/unit/M-PER-HR",
      "http://qudt.org/vocab/unit/CAL_TH-PER-SEC",
      "http://qudt.org/vocab/unit/MicroPA",
      "http://qudt.org/vocab/unit/MicroMOL-PER-M2-SEC",
      "http://qudt.org/vocab/unit/DEG_F-HR",
      "http://qudt.org/vocab/unit/IraqiDinar",
      "http://qudt.org/vocab/unit/KiloV-PER-M",
      "http://qudt.org/vocab/unit/M2-PER-HZ",
      "http://qudt.org/vocab/unit/MilliWB",
      "http://qudt.org/vocab/unit/SHANNON-PER-SEC",
      "http://qudt.org/vocab/unit/V_Ab-PER-CentiM",
      "http://qudt.org/vocab/unit/MicroMOL-PER-M2",
      "http://qudt.org/vocab/unit/NorwegianKrone",
      "http://qudt.org/vocab/unit/CFU",
      "http://qudt.org/vocab/unit/MegaHZ",
      "http://qudt.org/vocab/unit/BU_UK-PER-DAY",
      "http://qudt.org/vocab/unit/KiloPA-PER-K",
      "http://qudt.org/vocab/unit/KiloTONNE",
      "http://qudt.org/vocab/unit/MilliL-PER-CentiM2-SEC",
      "http://qudt.org/vocab/unit/REV",
      "http://qudt.org/vocab/unit/MX",
      "http://qudt.org/vocab/unit/LB-PER-DAY",
      "http://qudt.org/vocab/unit/MilliGM-PER-M2",
      "http://qudt.org/vocab/unit/MOL-PER-SEC",
      "http://qudt.org/vocab/unit/BIT",
      "http://qudt.org/vocab/unit/KiloCi",
      "http://qudt.org/vocab/unit/J-PER-SEC",
      "http://qudt.org/vocab/unit/GM-PER-MilliL",
      "http://qudt.org/vocab/unit/CentiM3-PER-K",
      "http://qudt.org/vocab/unit/M4",
      "http://qudt.org/vocab/unit/PlanckForce",
      "http://qudt.org/vocab/unit/N-PER-C",
      "http://qudt.org/vocab/unit/MDOLLAR-PER-FLIGHT",
      "http://qudt.org/vocab/unit/MegaTOE",
      "http://qudt.org/vocab/unit/IN",
      "http://qudt.org/vocab/unit/GM-PER-MOL",
      "http://qudt.org/vocab/unit/GAL_UK",
      "http://qudt.org/vocab/unit/GigaC",
      "http://qudt.org/vocab/unit/KiloBAR",
      "http://qudt.org/vocab/unit/PER-GigaEV2",
      "http://qudt.org/vocab/unit/MicroBQ-PER-KiloGM",
      "http://qudt.org/vocab/unit/GAL_UK-PER-HR",
      "http://qudt.org/vocab/unit/failures-in-time",
      "http://qudt.org/vocab/unit/EthiopianBirr",
      "http://qudt.org/vocab/unit/NanoFARAD",
      "http://qudt.org/vocab/unit/MilliC-PER-KiloGM",
      "http://qudt.org/vocab/unit/AMD",
      "http://qudt.org/vocab/unit/MilliMOL-PER-M3",
      "http://qudt.org/vocab/unit/MegaHZ-PER-K",
      "http://qudt.org/vocab/unit/TONNE-PER-SEC",
      "http://qudt.org/vocab/unit/MicroM-PER-MilliL",
      "http://qudt.org/vocab/unit/FT_HG",
      "http://qudt.org/vocab/unit/CAL_15_DEG_C",
      "http://qudt.org/vocab/unit/Manat",
      "http://qudt.org/vocab/unit/MicroGM-PER-KiloGM",
      "http://qudt.org/vocab/unit/K-PER-MIN",
      "http://qudt.org/vocab/unit/N-M-SEC-PER-RAD",
      "http://qudt.org/vocab/unit/TeraW-HR",
      "http://qudt.org/vocab/unit/ST",
      "http://qudt.org/vocab/unit/GM-PER-DEG_C",
      "http://qudt.org/vocab/unit/OZ-PER-FT2",
      "http://qudt.org/vocab/unit/M3-PER-C",
      "http://qudt.org/vocab/unit/CWT_SHORT",
      "http://qudt.org/vocab/unit/TrinidadAndTobagoDollar",
      "http://qudt.org/vocab/unit/LB_F",
      "http://qudt.org/vocab/unit/PINT_US",
      "http://qudt.org/vocab/unit/DRAM_US",
      "http://qudt.org/vocab/unit/BTU_IT-PER-HR-FT2-DEG_R",
      "http://qudt.org/vocab/unit/MilliV-PER-M",
      "http://qudt.org/vocab/unit/PSI-IN3-PER-SEC",
      "http://qudt.org/vocab/unit/KiloGM-M2",
      "http://qudt.org/vocab/unit/TON_Assay",
      "http://qudt.org/vocab/unit/KiloS-PER-M",
      "http://qudt.org/vocab/unit/EuropeanUnitOfAccount9",
      "http://qudt.org/vocab/unit/GigaW",
      "http://qudt.org/vocab/unit/MilliGM-PER-SEC",
      "http://qudt.org/vocab/unit/MicroGM-PER-M3",
      "http://qudt.org/vocab/unit/KiloM3-PER-SEC2",
      "http://qudt.org/vocab/unit/BBL_US",
      "http://qudt.org/vocab/unit/FemtoGM-PER-KiloGM",
      "http://qudt.org/vocab/unit/DEG_F-HR-FT2-PER-BTU_TH",
      "http://qudt.org/vocab/unit/IN-PER-SEC",
      "http://qudt.org/vocab/unit/MegaPA-L-PER-SEC",
      "http://qudt.org/vocab/unit/MegaEV-PER-SpeedOfLight",
      "http://qudt.org/vocab/unit/FRAME-PER-SEC",
      "http://qudt.org/vocab/unit/CAL_TH-PER-GM-K",
      "http://qudt.org/vocab/unit/DEG_F-HR-FT2-PER-BTU_IT",
      "http://qudt.org/vocab/unit/SR",
      "http://qudt.org/vocab/unit/SurinamDollar",
      "http://qudt.org/vocab/unit/PhilippinePeso",
      "http://qudt.org/vocab/unit/MilliRAD",
      "http://qudt.org/vocab/unit/M3-PER-KiloGM",
      "http://qudt.org/vocab/unit/YR_TROPICAL",
      "http://qudt.org/vocab/unit/DAY",
      "http://qudt.org/vocab/unit/DecaM3",
      "http://qudt.org/vocab/unit/PINT_US-PER-MIN",
      "http://qudt.org/vocab/unit/OHM-M",
      "http://qudt.org/vocab/unit/DanishKrone",
      "http://qudt.org/vocab/unit/SLUG-PER-MIN",
      "http://qudt.org/vocab/unit/ZimbabweDollar",
      "http://qudt.org/vocab/unit/M",
      "http://qudt.org/vocab/unit/FemtoM",
      "http://qudt.org/vocab/unit/J-PER-CentiM2-DAY",
      "http://qudt.org/vocab/unit/RomanianNeLeu",
      "http://qudt.org/vocab/unit/L-PER-MIN",
      "http://qudt.org/vocab/unit/GI_UK",
      "http://qudt.org/vocab/unit/BTU_IT-PER-FT2-SEC-DEG_F",
      "http://qudt.org/vocab/unit/PlanckPressure",
      "http://qudt.org/vocab/unit/MicroMOL-PER-KiloGM",
      "http://qudt.org/vocab/unit/W-PER-KiloGM",
      "http://qudt.org/vocab/unit/LunarMass",
      "http://qudt.org/vocab/unit/BAR",
      "http://qudt.org/vocab/unit/GM-PER-SEC",
      "http://qudt.org/vocab/unit/MicroN-M",
      "http://qudt.org/vocab/unit/DecaGM",
      "http://qudt.org/vocab/unit/PebiBYTE",
      "http://qudt.org/vocab/unit/CAL_IT-PER-GM",
      "http://qudt.org/vocab/unit/MegaC-PER-M2",
      "http://qudt.org/vocab/unit/GM_F-PER-CentiM2",
      "http://qudt.org/vocab/unit/LB_F-IN",
      "http://qudt.org/vocab/unit/CORD",
      "http://qudt.org/vocab/unit/L-PER-L",
      "http://qudt.org/vocab/unit/M-PER-SEC2",
      "http://qudt.org/vocab/unit/KiloPA_A",
      "http://qudt.org/vocab/unit/BTU_TH-IN-PER-FT2-HR-DEG_F",
      "http://qudt.org/vocab/unit/SAMPLE-PER-SEC",
      "http://qudt.org/vocab/unit/MilliGM-PER-MIN",
      "http://qudt.org/vocab/unit/C-PER-MOL",
      "http://qudt.org/vocab/unit/PER-MILLE-PER-PSI",
      "http://qudt.org/vocab/unit/HP-PER-V",
      "http://qudt.org/vocab/unit/SouthKoreanWon",
      "http://qudt.org/vocab/unit/FATH",
      "http://qudt.org/vocab/unit/DeciB_M",
      "http://qudt.org/vocab/unit/MilliGM-PER-CentiM2",
      "http://qudt.org/vocab/unit/A_Stat-PER-CentiM2",
      "http://qudt.org/vocab/unit/MilliT",
      "http://qudt.org/vocab/unit/LB-PER-YD3",
      "http://qudt.org/vocab/unit/MilliL-PER-HR",
      "http://qudt.org/vocab/unit/BU_US_DRY-PER-DAY",
      "http://qudt.org/vocab/unit/MilliM3-PER-M3",
      "http://qudt.org/vocab/unit/SLUG-PER-FT-SEC",
      "http://qudt.org/vocab/unit/DEG_C-CentiM",
      "http://qudt.org/vocab/unit/CentiM3-PER-SEC",
      "http://qudt.org/vocab/unit/FT_US",
      "http://qudt.org/vocab/unit/A-PER-J",
      "http://qudt.org/vocab/unit/ERG-PER-SEC",
      "http://qudt.org/vocab/unit/BARN",
      "http://qudt.org/vocab/unit/KiloW",
      "http://qudt.org/vocab/unit/DeciL-PER-GM",
      "http://qudt.org/vocab/unit/V-PER-SEC",
      "http://qudt.org/vocab/unit/EuropeanMonetaryUnit",
      "http://qudt.org/vocab/unit/NanoGM-PER-M3",
      "http://qudt.org/vocab/unit/PER-HR",
      "http://qudt.org/vocab/unit/GibiBYTE",
      "http://qudt.org/vocab/unit/AUD",
      "http://qudt.org/vocab/unit/AU",
      "http://qudt.org/vocab/unit/SLUG-PER-DAY",
      "http://qudt.org/vocab/unit/HART-PER-SEC",
      "http://qudt.org/vocab/unit/E_h",
      "http://qudt.org/vocab/unit/LB",
      "http://qudt.org/vocab/unit/KiloSEC",
      "http://qudt.org/vocab/unit/CentiMOL-PER-KiloGM",
      "http://qudt.org/vocab/unit/N-M-PER-M2",
      "http://qudt.org/vocab/unit/UruguayPeso",
      "http://qudt.org/vocab/unit/PER-SEC-SR",
      "http://qudt.org/vocab/unit/N-PER-KiloGM",
      "http://qudt.org/vocab/unit/MebiBYTE",
      "http://qudt.org/vocab/unit/KiloJ-PER-KiloGM-K",
      "http://qudt.org/vocab/unit/DeciM3-PER-DAY",
      "http://qudt.org/vocab/unit/CentiM2-MIN",
      "http://qudt.org/vocab/unit/J-PER-KiloGM",
      "http://qudt.org/vocab/unit/LB-MOL",
      "http://qudt.org/vocab/unit/W-PER-K",
      "http://qudt.org/vocab/unit/MegaA-PER-M2",
      "http://qudt.org/vocab/unit/Pennyweight",
      "http://qudt.org/vocab/unit/GM-PER-DAY",
      "http://qudt.org/vocab/unit/KiloGM-K",
      "http://qudt.org/vocab/unit/MilliGM-PER-M2-HR",
      "http://qudt.org/vocab/unit/SEC-PER-RAD-M3",
      "http://qudt.org/vocab/unit/BTU_IT-PER-HR",
      "http://qudt.org/vocab/unit/DEGREE_BAUME_US_LIGHT",
      "http://qudt.org/vocab/unit/Ci",
      "http://qudt.org/vocab/unit/BTU_IT-IN-PER-FT2-HR-DEG_F",
      "http://qudt.org/vocab/unit/TOE",
      "http://qudt.org/vocab/unit/KiloC-PER-M2",
      "http://qudt.org/vocab/unit/CaymanIslandsDollar",
      "http://qudt.org/vocab/unit/PicoGM-PER-GM",
      "http://qudt.org/vocab/unit/PER-MicroM",
      "http://qudt.org/vocab/unit/N-M-PER-RAD",
      "http://qudt.org/vocab/unit/FUR_Long",
      "http://qudt.org/vocab/unit/PicoMOL-PER-L-HR",
      "http://qudt.org/vocab/unit/L-PER-K",
      "http://qudt.org/vocab/unit/YD",
      "http://qudt.org/vocab/unit/PDL-PER-FT2",
      "http://qudt.org/vocab/unit/NanoGM-PER-DAY",
      "http://qudt.org/vocab/unit/PSI-L-PER-SEC",
      "http://qudt.org/vocab/unit/Lari",
      "http://qudt.org/vocab/unit/Gamma",
      "http://qudt.org/vocab/unit/MegaC",
      "http://qudt.org/vocab/unit/PHOT",
      "http://qudt.org/vocab/unit/QT_US-PER-DAY",
      "http://qudt.org/vocab/unit/BTU_TH-PER-SEC",
      "http://qudt.org/vocab/unit/OZ_VOL_UK-PER-DAY",
      "http://qudt.org/vocab/unit/PERCENT_RH",
      "http://qudt.org/vocab/unit/MilliIN",
      "http://qudt.org/vocab/unit/CARAT",
      "http://qudt.org/vocab/unit/DYN-PER-CentiM",
      "http://qudt.org/vocab/unit/NewTaiwanDollar",
      "http://qudt.org/vocab/unit/MilliSEC",
      "http://qudt.org/vocab/unit/PlanckLength",
      "http://qudt.org/vocab/unit/V-PER-K",
      "http://qudt.org/vocab/unit/FT-LB_F-SEC",
      "http://qudt.org/vocab/unit/W-PER-CentiM2",
      "http://qudt.org/vocab/unit/CentiM3-PER-DAY",
      "http://qudt.org/vocab/unit/CentiPOISE",
      "http://qudt.org/vocab/unit/PER-GM",
      "http://qudt.org/vocab/unit/PERCENT-PER-DAY",
      "http://qudt.org/vocab/unit/CAL_TH-PER-GM-DEG_C",
      "http://qudt.org/vocab/unit/V_Stat-PER-CentiM",
      "http://qudt.org/vocab/unit/MilliARCSEC",
      "http://qudt.org/vocab/unit/KiloPA-PER-BAR",
      "http://qudt.org/vocab/unit/MilliDEG_C",
      "http://qudt.org/vocab/unit/H-PER-M",
      "http://qudt.org/vocab/unit/Dalasi",
      "http://qudt.org/vocab/unit/KiloMOL-PER-SEC",
      "http://qudt.org/vocab/unit/KiloCAL_TH-PER-HR",
      "http://qudt.org/vocab/unit/POISE",
      "http://qudt.org/vocab/unit/LB_T",
      "http://qudt.org/vocab/unit/RAD",
      "http://qudt.org/vocab/unit/BQ-SEC-PER-M3",
      "http://qudt.org/vocab/unit/NanoFARAD-PER-M",
      "http://qudt.org/vocab/unit/Paanga",
      "http://qudt.org/vocab/unit/UgandaShilling",
      "http://qudt.org/vocab/unit/CAL_IT-PER-SEC-CentiM2-K",
      "http://qudt.org/vocab/unit/BEAT-PER-MIN",
      "http://qudt.org/vocab/unit/MilliM-PER-DAY",
      "http://qudt.org/vocab/unit/MicroMOL-PER-MicroMOL-DAY",
      "http://qudt.org/vocab/unit/MilliL-PER-L",
      "http://qudt.org/vocab/unit/M2-SR",
      "http://qudt.org/vocab/unit/W-SEC",
      "http://qudt.org/vocab/unit/PA-M",
      "http://qudt.org/vocab/unit/Denier",
      "http://qudt.org/vocab/unit/KiloV-A",
      "http://qudt.org/vocab/unit/MegaJ-PER-M3",
      "http://qudt.org/vocab/unit/OZ_F-IN",
      "http://qudt.org/vocab/unit/W-PER-M2-K4",
      "http://qudt.org/vocab/unit/GM-PER-CentiM2",
      "http://qudt.org/vocab/unit/OZ",
      "http://qudt.org/vocab/unit/MilliC",
      "http://qudt.org/vocab/unit/KiloGAUSS",
      "http://qudt.org/vocab/unit/PK_US_DRY-PER-DAY",
      "http://qudt.org/vocab/unit/GAL_UK-PER-SEC",
      "http://qudt.org/vocab/unit/PA-PER-M",
      "http://qudt.org/vocab/unit/V-SEC-PER-M",
      "http://qudt.org/vocab/unit/HP_Boiler",
      "http://qudt.org/vocab/unit/SEC-PER-M",
      "http://qudt.org/vocab/unit/BTU_IT-PER-MIN",
      "http://qudt.org/vocab/unit/KiloGM-PER-CentiM2",
      "http://qudt.org/vocab/unit/MicroMOL-PER-SEC",
      "http://qudt.org/vocab/unit/V_Stat",
      "http://qudt.org/vocab/unit/S-PER-M",
      "http://qudt.org/vocab/unit/KiloV-A_Reactive",
      "http://qudt.org/vocab/unit/L-PER-MOL",
      "http://qudt.org/vocab/unit/PA-PER-K",
      "http://qudt.org/vocab/unit/Hundredweight_UK",
      "http://qudt.org/vocab/unit/ERLANG",
      "http://qudt.org/vocab/unit/KiloGM_F-M-PER-CentiM2",
      "http://qudt.org/vocab/unit/KenyanShilling",
      "http://qudt.org/vocab/unit/OZ-IN",
      "http://qudt.org/vocab/unit/Pula",
      "http://qudt.org/vocab/unit/CentiM-PER-SEC2",
      "http://qudt.org/vocab/unit/BruneiDollar",
      "http://qudt.org/vocab/unit/PA2-PER-SEC2",
      "http://qudt.org/vocab/unit/W-PER-M2",
      "http://qudt.org/vocab/unit/PINT_UK-PER-HR",
      "http://qudt.org/vocab/unit/PER-PA-SEC",
      "http://qudt.org/vocab/unit/BTU_IT-PER-SEC-FT2",
      "http://qudt.org/vocab/unit/KiloLB_F-FT-PER-A",
      "http://qudt.org/vocab/unit/MOL-PER-M3-SEC",
      "http://qudt.org/vocab/unit/FT-PDL",
      "http://qudt.org/vocab/unit/DEGREE_PLATO",
      "http://qudt.org/vocab/unit/MOL-PER-KiloGM",
      "http://qudt.org/vocab/unit/GM-PER-M3",
      "http://qudt.org/vocab/unit/MicroV-PER-M",
      "http://qudt.org/vocab/unit/KiloGM-PER-M",
      "http://qudt.org/vocab/unit/M3",
      "http://qudt.org/vocab/unit/PicoS-PER-M",
      "http://qudt.org/vocab/unit/MOL-PER-GM-HR",
      "http://qudt.org/vocab/unit/PA-PER-BAR",
      "http://qudt.org/vocab/unit/BBL_US_DRY",
      "http://qudt.org/vocab/unit/DecaC",
      "http://qudt.org/vocab/unit/KiloGM-PER-HR",
      "http://qudt.org/vocab/unit/PER-MilliM3",
      "http://qudt.org/vocab/unit/MilliMOL-PER-M2",
      "http://qudt.org/vocab/unit/TON_Metric",
      "http://qudt.org/vocab/unit/Dobra",
      "http://qudt.org/vocab/unit/Stone_UK",
      "http://qudt.org/vocab/unit/MilliM_HG",
      "http://qudt.org/vocab/unit/TON_LONG",
      "http://qudt.org/vocab/unit/GM-PER-GM",
      "http://qudt.org/vocab/unit/KiloS",
      "http://qudt.org/vocab/unit/NanoGM",
      "http://qudt.org/vocab/unit/NanoSEC",
      "http://qudt.org/vocab/unit/M3-PER-DAY",
      "http://qudt.org/vocab/unit/LB-IN",
      "http://qudt.org/vocab/unit/OZ_VOL_UK-PER-SEC",
      "http://qudt.org/vocab/unit/PER-SEC2",
      "http://qudt.org/vocab/unit/PicoMOL-PER-L",
      "http://qudt.org/vocab/unit/KiloGM-PER-L",
      "http://qudt.org/vocab/unit/PER-PA",
      "http://qudt.org/vocab/unit/LibyanDinar",
      "http://qudt.org/vocab/unit/STILB",
      "http://qudt.org/vocab/unit/SUSCEPTIBILITY_ELEC",
      "http://qudt.org/vocab/unit/SudanesePound",
      "http://qudt.org/vocab/unit/M2-PER-HA",
      "http://qudt.org/vocab/unit/MilliA",
      "http://qudt.org/vocab/unit/DeciB_C",
      "http://qudt.org/vocab/unit/MilliRAD_R-PER-HR",
      "http://qudt.org/vocab/unit/MilliGM-PER-M3",
      "http://qudt.org/vocab/unit/IN4",
      "http://qudt.org/vocab/unit/M2-PER-N",
      "http://qudt.org/vocab/unit/MegaN",
      "http://qudt.org/vocab/unit/KiloGM-PER-SEC-M2",
      "http://qudt.org/vocab/unit/DEGREE_API",
      "http://qudt.org/vocab/unit/DEATHS-PER-1000000I-YR",
      "http://qudt.org/vocab/unit/UnidadesDeFormento",
      "http://qudt.org/vocab/unit/FUR",
      "http://qudt.org/vocab/unit/ERG-PER-GM-SEC",
      "http://qudt.org/vocab/unit/TON_F_US",
      "http://qudt.org/vocab/unit/CAL_MEAN",
      "http://qudt.org/vocab/unit/RAD_R",
      "http://qudt.org/vocab/unit/Nakfa",
      "http://qudt.org/vocab/unit/C3-M-PER-J2",
      "http://qudt.org/vocab/unit/DecaARE",
      "http://qudt.org/vocab/unit/LB_F-PER-IN2-DEG_F",
      "http://qudt.org/vocab/unit/KiloGM_F-PER-CentiM2",
      "http://qudt.org/vocab/unit/FT3-PER-DEG_F",
      "http://qudt.org/vocab/unit/MO_MeanJulian",
      "http://qudt.org/vocab/unit/MIN_Sidereal",
      "http://qudt.org/vocab/unit/MegaS-PER-M",
      "http://qudt.org/vocab/unit/N-PER-CentiM",
      "http://qudt.org/vocab/unit/LaoKip",
      "http://qudt.org/vocab/unit/LB-PER-FT2",
      "http://qudt.org/vocab/unit/PER-M-SR",
      "http://qudt.org/vocab/unit/ARCMIN",
      "http://qudt.org/vocab/unit/MicroS",
      "http://qudt.org/vocab/unit/ARCSEC",
      "http://qudt.org/vocab/unit/BAR-PER-BAR",
      "http://qudt.org/vocab/unit/PER-SEC-M2",
      "http://qudt.org/vocab/unit/CAL_IT",
      "http://qudt.org/vocab/unit/RAD-PER-SEC2",
      "http://qudt.org/vocab/unit/J-PER-HR",
      "http://qudt.org/vocab/unit/CentiM-PER-K",
      "http://qudt.org/vocab/unit/HectoPA-PER-BAR",
      "http://qudt.org/vocab/unit/MilliGM-PER-HR",
      "http://qudt.org/vocab/unit/MegaJ-PER-M2",
      "http://qudt.org/vocab/unit/PA-SEC-PER-BAR",
      "http://qudt.org/vocab/unit/PER-NanoM",
      "http://qudt.org/vocab/unit/MegaA",
      "http://qudt.org/vocab/unit/Euro",
      "http://qudt.org/vocab/unit/N-PER-M",
      "http://qudt.org/vocab/unit/V-A_Reactive-HR",
      "http://qudt.org/vocab/unit/IN-PER-SEC2",
      "http://qudt.org/vocab/unit/CentiC",
      "http://qudt.org/vocab/unit/PlanckDensity",
      "http://qudt.org/vocab/unit/B",
      "http://qudt.org/vocab/unit/C-PER-M3",
      "http://qudt.org/vocab/unit/PicoMOL-PER-KiloGM",
      "http://qudt.org/vocab/unit/MOL-PER-M2-SEC-M",
      "http://qudt.org/vocab/unit/SLUG-PER-HR",
      "http://qudt.org/vocab/unit/MilliM-PER-SEC",
      "http://qudt.org/vocab/unit/MicroH-PER-M",
      "http://qudt.org/vocab/unit/NamibianDollar",
      "http://qudt.org/vocab/unit/W-HR-PER-M3",
      "http://qudt.org/vocab/unit/W-PER-M2-PA",
      "http://qudt.org/vocab/unit/C_Stat-PER-MOL",
      "http://qudt.org/vocab/unit/IranianRial",
      "http://qudt.org/vocab/unit/TONNE-PER-M3",
      "http://qudt.org/vocab/unit/L-PER-KiloGM",
      "http://qudt.org/vocab/unit/N-SEC-PER-M",
      "http://qudt.org/vocab/unit/J-PER-M4",
      "http://qudt.org/vocab/unit/BTU_IT-PER-LB_F-DEG_F",
      "http://qudt.org/vocab/unit/MilliGM-PER-M2-DAY",
      "http://qudt.org/vocab/unit/PT",
      "http://qudt.org/vocab/unit/MicroRAD",
      "http://qudt.org/vocab/unit/J",
      "http://qudt.org/vocab/unit/UICFranc",
      "http://qudt.org/vocab/unit/FT-PER-SEC2",
      "http://qudt.org/vocab/unit/KiloMOL",
      "http://qudt.org/vocab/unit/M3-PER-MIN",
      "http://qudt.org/vocab/unit/KiloCAL-PER-GM-DEG_C",
      "http://qudt.org/vocab/unit/PA-SEC",
      "http://qudt.org/vocab/unit/ATM_T",
      "http://qudt.org/vocab/unit/KibiBYTE",
      "http://qudt.org/vocab/unit/KiloGM-PER-DAY",
      "http://qudt.org/vocab/unit/MilliH-PER-KiloOHM",
      "http://qudt.org/vocab/unit/MilliOHM",
      "http://qudt.org/vocab/unit/MilliS-PER-M",
      "http://qudt.org/vocab/unit/DPI",
      "http://qudt.org/vocab/unit/FARAD-PER-KiloM",
      "http://qudt.org/vocab/unit/CD",
      "http://qudt.org/vocab/unit/KiloGM-CentiM2",
      "http://qudt.org/vocab/unit/L",
      "http://qudt.org/vocab/unit/NUM-PER-HA",
      "http://qudt.org/vocab/unit/ZambianKwacha",
      "http://qudt.org/vocab/unit/NUM-PER-NanoL",
      "http://qudt.org/vocab/unit/HeartBeat",
      "http://qudt.org/vocab/unit/EV-PER-ANGSTROM",
      "http://qudt.org/vocab/unit/KiloGM-PER-KiloMOL",
      "http://qudt.org/vocab/unit/BYR",
      "http://qudt.org/vocab/unit/PA-PER-SEC",
      "http://qudt.org/vocab/unit/IU",
      "http://qudt.org/vocab/unit/T-SEC",
      "http://qudt.org/vocab/unit/CentiM-SEC-DEG_C",
      "http://qudt.org/vocab/unit/DRAM_UK",
      "http://qudt.org/vocab/unit/MicroIN",
      "http://qudt.org/vocab/unit/LM-SEC",
      "http://qudt.org/vocab/unit/PPTH-PER-HR",
      "http://qudt.org/vocab/unit/MicroGAL-PER-M",
      "http://qudt.org/vocab/unit/M2-K",
      "http://qudt.org/vocab/unit/KiloGM-PER-M2",
      "http://qudt.org/vocab/unit/J-PER-KiloGM-K-PA",
      "http://qudt.org/vocab/unit/REM",
      "http://qudt.org/vocab/unit/M-K-PER-W",
      "http://qudt.org/vocab/unit/CentiM",
      "http://qudt.org/vocab/unit/LatvianLats",
      "http://qudt.org/vocab/unit/W-M-PER-M2-SR",
      "http://qudt.org/vocab/unit/Standard",
      "http://qudt.org/vocab/unit/LB-PER-FT3",
      "http://qudt.org/vocab/unit/LB-PER-GAL_UK",
      "http://qudt.org/vocab/unit/KiloCAL-PER-CentiM-SEC-DEG_C",
      "http://qudt.org/vocab/unit/H-PER-OHM",
      "http://qudt.org/vocab/unit/MilliBQ-PER-KiloGM",
      "http://qudt.org/vocab/unit/MHO_Stat",
      "http://qudt.org/vocab/unit/GM",
      "http://qudt.org/vocab/unit/YemeniRial",
      "http://qudt.org/vocab/unit/PERMITTIVITY_REL",
      "http://qudt.org/vocab/unit/PER-MOL",
      "http://qudt.org/vocab/unit/DEG_F-PER-SEC",
      "http://qudt.org/vocab/unit/GI_UK-PER-MIN",
      "http://qudt.org/vocab/unit/MOL-PER-M2",
      "http://qudt.org/vocab/unit/LA",
      "http://qudt.org/vocab/unit/PicoA",
      "http://qudt.org/vocab/unit/MegaEV-PER-CentiM",
      "http://qudt.org/vocab/unit/BREATH-PER-MIN",
      "http://qudt.org/vocab/unit/KiloA-PER-M",
      "http://qudt.org/vocab/unit/PER-M-NanoM-SR",
      "http://qudt.org/vocab/unit/PPM",
      "http://qudt.org/vocab/unit/NUM-PER-M3",
      "http://qudt.org/vocab/unit/PER-J-M3",
      "http://qudt.org/vocab/unit/CostaRicanColon",
      "http://qudt.org/vocab/unit/BelizeDollar",
      "http://qudt.org/vocab/unit/MicroC-PER-M3",
      "http://qudt.org/vocab/unit/GI_UK-PER-DAY",
      "http://qudt.org/vocab/unit/IndianRupee",
      "http://qudt.org/vocab/unit/YottaC",
      "http://qudt.org/vocab/unit/DYN-SEC-PER-CentiM",
      "http://qudt.org/vocab/unit/QUAD",
      "http://qudt.org/vocab/unit/AT-PER-M",
      "http://qudt.org/vocab/unit/KiloGM-PER-M3-SEC",
      "http://qudt.org/vocab/unit/AttoC",
      "http://qudt.org/vocab/unit/GALILEO",
      "http://qudt.org/vocab/unit/CAL_TH-PER-SEC-CentiM-K",
      "http://qudt.org/vocab/unit/MilliH",
      "http://qudt.org/vocab/unit/M3-PER-M3",
      "http://qudt.org/vocab/unit/PER-L",
      "http://qudt.org/vocab/unit/MicroMHO",
      "http://qudt.org/vocab/unit/MilliV-PER-MIN",
      "http://qudt.org/vocab/unit/KY",
      "http://qudt.org/vocab/unit/MilliR",
      "http://qudt.org/vocab/unit/CordobaOro",
      "http://qudt.org/vocab/unit/EV",
      "http://qudt.org/vocab/unit/PA2-SEC",
      "http://qudt.org/vocab/unit/ExbiBYTE",
      "http://qudt.org/vocab/unit/OZ-PER-YD2",
      "http://qudt.org/vocab/unit/GRAIN-PER-GAL_US",
      "http://qudt.org/vocab/unit/SLUG-PER-FT2",
      "http://qudt.org/vocab/unit/CentiST",
      "http://qudt.org/vocab/unit/PA-SEC-PER-M",
      "http://qudt.org/vocab/unit/WB",
      "http://qudt.org/vocab/unit/KiloM",
      "http://qudt.org/vocab/unit/PA-PER-HR",
      "http://qudt.org/vocab/unit/KiloBYTE-PER-SEC",
      "http://qudt.org/vocab/unit/RAYL",
      "http://qudt.org/vocab/unit/AT-PER-IN",
      "http://qudt.org/vocab/unit/MicroGM-PER-MilliL",
      "http://qudt.org/vocab/unit/MoroccanDirham",
      "http://qudt.org/vocab/unit/MOL-PER-KiloGM-PA",
      "http://qudt.org/vocab/unit/PlanckMomentum",
      "http://qudt.org/vocab/unit/LB-PER-FT",
      "http://qudt.org/vocab/unit/MilliGM-PER-KiloGM",
      "http://qudt.org/vocab/unit/DEG_F-PER-SEC2",
      "http://qudt.org/vocab/unit/K-M-PER-SEC",
      "http://qudt.org/vocab/unit/LB-PER-FT-SEC",
      "http://qudt.org/vocab/unit/PERMEABILITY_REL",
      "http://qudt.org/vocab/unit/TeraBYTE",
      "http://qudt.org/vocab/unit/AC-FT",
      "http://qudt.org/vocab/unit/MilliL-PER-MIN",
      "http://qudt.org/vocab/unit/BHD",
      "http://qudt.org/vocab/unit/PER-M-K",
      "http://qudt.org/vocab/unit/MilliW-PER-M2-NanoM-SR",
      "http://qudt.org/vocab/unit/MicroL",
      "http://qudt.org/vocab/unit/KiloGM",
      "http://qudt.org/vocab/unit/IN2-PER-SEC",
      "http://qudt.org/vocab/unit/JordanianDinar",
      "http://qudt.org/vocab/unit/V-PER-CentiM",
      "http://qudt.org/vocab/unit/PlanckVolt",
      "http://qudt.org/vocab/unit/Hundredweight_US",
      "http://qudt.org/vocab/unit/TONNE-PER-MIN",
      "http://qudt.org/vocab/unit/TON_US-PER-HR",
      "http://qudt.org/vocab/unit/GigaHZ-M",
      "http://qudt.org/vocab/unit/PPTR_VOL",
      "http://qudt.org/vocab/unit/MicroOHM",
      "http://qudt.org/vocab/unit/GI_US",
      "http://qudt.org/vocab/unit/HectoPA",
      "http://qudt.org/vocab/unit/GM-PER-HR",
      "http://qudt.org/vocab/unit/HA",
      "http://qudt.org/vocab/unit/XPF",
      "http://qudt.org/vocab/unit/DeciC",
      "http://qudt.org/vocab/unit/C_Ab",
      "http://qudt.org/vocab/unit/KiloMOL-PER-KiloGM",
      "http://qudt.org/vocab/unit/NUM-PER-MicroL",
      "http://qudt.org/vocab/unit/EV-PER-M",
      "http://qudt.org/vocab/unit/KiloV-A_Reactive-HR",
      "http://qudt.org/vocab/unit/MilliMOL-PER-KiloGM",
      "http://qudt.org/vocab/unit/Naira",
      "http://qudt.org/vocab/unit/AttoJ-SEC",
      "http://qudt.org/vocab/unit/PCA",
      "http://qudt.org/vocab/unit/MalteseLira",
      "http://qudt.org/vocab/unit/BARYE",
      "http://qudt.org/vocab/unit/OZ-FT",
      "http://qudt.org/vocab/unit/JapaneseYen",
      "http://qudt.org/vocab/unit/MicroSV",
      "http://qudt.org/vocab/unit/NetherlandsAntillianGuilder",
      "http://qudt.org/vocab/unit/V",
      "http://qudt.org/vocab/unit/ROD",
      "http://qudt.org/vocab/unit/DominicanPeso",
      "http://qudt.org/vocab/unit/LY",
      "http://qudt.org/vocab/unit/BTU_IT-PER-FT2",
      "http://qudt.org/vocab/unit/N-PER-M3",
      "http://qudt.org/vocab/unit/FT-PER-DEG_F",
      "http://qudt.org/vocab/unit/DEG-PER-MIN",
      "http://qudt.org/vocab/unit/PlanckEnergy",
      "http://qudt.org/vocab/unit/XAF",
      "http://qudt.org/vocab/unit/MicroM3",
      "http://qudt.org/vocab/unit/MicroMOL-PER-M2-HR",
      "http://qudt.org/vocab/unit/CWT_LONG",
      "http://qudt.org/vocab/unit/PicoW-PER-M2",
      "http://qudt.org/vocab/unit/GigaEV",
      "http://qudt.org/vocab/unit/MilliL-PER-K",
      "http://qudt.org/vocab/unit/GT",
      "http://qudt.org/vocab/unit/CapeVerdeEscudo",
      "http://qudt.org/vocab/unit/BU_UK-PER-MIN",
      "http://qudt.org/vocab/unit/T",
      "http://qudt.org/vocab/unit/KiloCAL_IT",
      "http://qudt.org/vocab/unit/MilliW-PER-M2",
      "http://qudt.org/vocab/unit/FT-PER-SEC",
      "http://qudt.org/vocab/unit/MegaV-A-HR",
      "http://qudt.org/vocab/unit/MegaLB_F",
      "http://qudt.org/vocab/unit/W-PER-M3",
      "http://qudt.org/vocab/unit/BBL_UK_PET-PER-MIN",
      "http://qudt.org/vocab/unit/DEG_C-PER-K",
      "http://qudt.org/vocab/unit/GAL_US_DRY",
      "http://qudt.org/vocab/unit/NP",
      "http://qudt.org/vocab/unit/ERG",
      "http://qudt.org/vocab/unit/GoldFranc",
      "http://qudt.org/vocab/unit/Rupiah",
      "http://qudt.org/vocab/unit/PSI",
      "http://qudt.org/vocab/unit/CroatianKuna",
      "http://qudt.org/vocab/unit/AttoJ",
      "http://qudt.org/vocab/unit/PINT_US-PER-SEC",
      "http://qudt.org/vocab/unit/PER-WB",
      "http://qudt.org/vocab/unit/KiloMOL-PER-HR",
      "http://qudt.org/vocab/unit/BTU_MEAN",
      "http://qudt.org/vocab/unit/EastCaribbeanDollar",
      "http://qudt.org/vocab/unit/PA-M3-PER-SEC",
      "http://qudt.org/vocab/unit/KiloA",
      "http://qudt.org/vocab/unit/PA-M-PER-SEC",
      "http://qudt.org/vocab/unit/FrancCongolais",
      "http://qudt.org/vocab/unit/Som",
      "http://qudt.org/vocab/unit/PicoMOL-PER-M3-SEC",
      "http://qudt.org/vocab/unit/MilliS",
      "http://qudt.org/vocab/unit/EV-PER-K",
      "http://qudt.org/vocab/unit/HR",
      "http://qudt.org/vocab/unit/N-M",
      "http://qudt.org/vocab/unit/PicoGM-PER-KiloGM",
      "http://qudt.org/vocab/unit/KiloCAL-PER-CentiM2",
      "http://qudt.org/vocab/unit/MicroT",
      "http://qudt.org/vocab/unit/TON_UK-PER-YD3",
      "http://qudt.org/vocab/unit/PicoC",
      "http://qudt.org/vocab/unit/IN2",
      "http://qudt.org/vocab/unit/MoldovanLeu",
      "http://qudt.org/vocab/unit/MOHM",
      "http://qudt.org/vocab/unit/MHO",
      "http://qudt.org/vocab/unit/M2-HZ3",
      "http://qudt.org/vocab/unit/DYN-CentiM",
      "http://qudt.org/vocab/unit/FC",
      "http://qudt.org/vocab/unit/Vatu",
      "http://qudt.org/vocab/unit/MalagasyAriary",
      "http://qudt.org/vocab/unit/FT-LB_F-PER-HR",
      "http://qudt.org/vocab/unit/TONNE-PER-HR",
      "http://qudt.org/vocab/unit/LB-DEG_F",
      "http://qudt.org/vocab/unit/FT2-PER-HR",
      "http://qudt.org/vocab/unit/BFT",
      "http://qudt.org/vocab/unit/BolivianMvdol",
      "http://qudt.org/vocab/unit/KiloR",
      "http://qudt.org/vocab/unit/MOL",
      "http://qudt.org/vocab/unit/ERG-PER-CentiM3",
      "http://qudt.org/vocab/unit/V_Stat-CentiM",
      "http://qudt.org/vocab/unit/AZN",
      "http://qudt.org/vocab/unit/BBL",
      "http://qudt.org/vocab/unit/DEG_C",
      "http://qudt.org/vocab/unit/PicoGM-PER-L",
      "http://qudt.org/vocab/unit/MilLength",
      "http://qudt.org/vocab/unit/KIP_F-PER-IN2",
      "http://qudt.org/vocab/unit/M2-PER-GM_DRY",
      "http://qudt.org/vocab/unit/K-PER-M",
      "http://qudt.org/vocab/unit/MicroH-PER-OHM",
      "http://qudt.org/vocab/unit/A-PER-MilliM2",
      "http://qudt.org/vocab/unit/DeciS-PER-M",
      "http://qudt.org/vocab/unit/PicoGM-PER-MilliL",
      "http://qudt.org/vocab/unit/Gold-OunceTroy",
      "http://qudt.org/vocab/unit/BAR-L-PER-SEC",
      "http://qudt.org/vocab/unit/MOL-DEG_C",
      "http://qudt.org/vocab/unit/M-PER-YR",
      "http://qudt.org/vocab/unit/J-PER-KiloGM-K-M3",
      "http://qudt.org/vocab/unit/KiloCAL_Mean",
      "http://qudt.org/vocab/unit/K-PER-K",
      "http://qudt.org/vocab/unit/MegaV-A_Reactive",
      "http://qudt.org/vocab/unit/KiloGM-PER-M-HR",
      "http://qudt.org/vocab/unit/M2-PER-HZ2",
      "http://qudt.org/vocab/unit/A-PER-MilliM",
      "http://qudt.org/vocab/unit/BTU_IT-PER-FT3",
      "http://qudt.org/vocab/unit/HP",
      "http://qudt.org/vocab/unit/S-PER-CentiM",
      "http://qudt.org/vocab/unit/NUM-PER-CentiM-KiloYR",
      "http://qudt.org/vocab/unit/GigaC-PER-M3",
      "http://qudt.org/vocab/unit/QT_UK-PER-SEC",
      "http://qudt.org/vocab/unit/ConvertibleMark",
      "http://qudt.org/vocab/unit/PER-FT3",
      "http://qudt.org/vocab/unit/BIT-PER-SEC",
      "http://qudt.org/vocab/unit/PPTR",
      "http://qudt.org/vocab/unit/DEG_C-PER-M",
      "http://qudt.org/vocab/unit/MOL-PER-M3",
      "http://qudt.org/vocab/unit/BAR-PER-K",
      "http://qudt.org/vocab/unit/MilliL-PER-DAY",
      "http://qudt.org/vocab/unit/PER-MilliSEC",
      "http://qudt.org/vocab/unit/MOL-PER-M2-SEC-M-SR",
      "http://qudt.org/vocab/unit/MicroMOL-PER-MOL",
      "http://qudt.org/vocab/unit/K",
      "http://qudt.org/vocab/unit/ExaJ",
      "http://qudt.org/vocab/unit/Z",
      "http://qudt.org/vocab/unit/A-PER-M2",
      "http://qudt.org/vocab/unit/MegaEV",
      "http://qudt.org/vocab/unit/YD3-PER-MIN",
      "http://qudt.org/vocab/unit/TON_US-PER-DAY",
      "http://qudt.org/vocab/unit/LB-PER-MIN",
      "http://qudt.org/vocab/unit/HectoPA-PER-K",
      "http://qudt.org/vocab/unit/J-PER-M",
      "http://qudt.org/vocab/unit/BQ-PER-M3",
      "http://qudt.org/vocab/unit/DecaL",
      "http://qudt.org/vocab/unit/GRAY",
      "http://qudt.org/vocab/unit/Kyat",
      "http://qudt.org/vocab/unit/POISE-PER-BAR",
      "http://qudt.org/vocab/unit/M2-PER-K",
      "http://qudt.org/vocab/unit/J-PER-MOL-K",
      "http://qudt.org/vocab/unit/T-M",
      "http://qudt.org/vocab/unit/CLO",
      "http://qudt.org/vocab/unit/KiloCAL-PER-MOL-DEG_C",
      "http://qudt.org/vocab/unit/ANGSTROM",
      "http://qudt.org/vocab/unit/CentiN-M",
      "http://qudt.org/vocab/unit/KiloV-A-HR",
      "http://qudt.org/vocab/unit/NanoGM-PER-MilliL",
      "http://qudt.org/vocab/unit/PlanckTime",
      "http://qudt.org/vocab/unit/OZ_VOL_UK",
      "http://qudt.org/vocab/unit/A-SEC",
      "http://qudt.org/vocab/unit/M2-PER-SEC",
      "http://qudt.org/vocab/unit/MicroGM-PER-L",
      "http://qudt.org/vocab/unit/AWG",
      "http://qudt.org/vocab/unit/GM-PER-M2",
      "http://qudt.org/vocab/unit/KiloGM-PER-MilliM",
      "http://qudt.org/vocab/unit/AT",
      "http://qudt.org/vocab/unit/PER-KiloM",
      "http://qudt.org/vocab/unit/GAL_US-PER-HR",
      "http://qudt.org/vocab/unit/CentiM2-PER-CentiM3",
      "http://qudt.org/vocab/unit/MalawiKwacha",
      "http://qudt.org/vocab/unit/GI_US-PER-HR",
      "http://qudt.org/vocab/unit/SEC2",
      "http://qudt.org/vocab/unit/DeciM3-PER-M3",
      "http://qudt.org/vocab/unit/PER-M3-SEC",
      "http://qudt.org/vocab/unit/EuropeanUnitOfAccount17",
      "http://qudt.org/vocab/unit/KiloGM_F-PER-MilliM2",
      "http://qudt.org/vocab/unit/BTU_IT-PER-LB_F",
      "http://qudt.org/vocab/unit/FM",
      "http://qudt.org/vocab/unit/A-M2",
      "http://qudt.org/vocab/unit/GAL_US",
      "http://qudt.org/vocab/unit/MicroFARAD-PER-KiloM",
      "http://qudt.org/vocab/unit/MilliA-HR",
      "http://qudt.org/vocab/unit/LithuanianLitas",
      "http://qudt.org/vocab/unit/UAEDirham",
      "http://qudt.org/vocab/unit/MicroGRAY",
      "http://qudt.org/vocab/unit/BQ-PER-M2",
      "http://qudt.org/vocab/unit/KAT",
      "http://qudt.org/vocab/unit/CentiM3-PER-MIN",
      "http://qudt.org/vocab/unit/GAL_IMP",
      "http://qudt.org/vocab/unit/CentiPOISE-PER-BAR",
      "http://qudt.org/vocab/unit/Zloty",
      "http://qudt.org/vocab/unit/PA-PER-MIN",
      "http://qudt.org/vocab/unit/KiloPOND",
      "http://qudt.org/vocab/unit/MilliMOL",
      "http://qudt.org/vocab/unit/PSU",
      "http://qudt.org/vocab/unit/DEG_R-PER-SEC",
      "http://qudt.org/vocab/unit/MilliBQ-PER-M2-DAY",
      "http://qudt.org/vocab/unit/Metical",
      "http://qudt.org/vocab/unit/PA-L-PER-SEC",
      "http://qudt.org/vocab/unit/A-PER-M2-K2",
      "http://qudt.org/vocab/unit/ERG-PER-G",
      "http://qudt.org/vocab/unit/A_Ab-PER-CentiM2",
      "http://qudt.org/vocab/unit/MicroJ",
      "http://qudt.org/vocab/unit/DEG_R-PER-MIN",
      "http://qudt.org/vocab/unit/CentiM-PER-KiloYR",
      "http://qudt.org/vocab/unit/C-PER-CentiM3",
      "http://qudt.org/vocab/unit/HR_Sidereal",
      "http://qudt.org/vocab/unit/CAL_TH-PER-MIN",
      "http://qudt.org/vocab/unit/TeraHZ",
      "http://qudt.org/vocab/unit/N-M-PER-A",
      "http://qudt.org/vocab/unit/MicroBQ",
      "http://qudt.org/vocab/unit/REV-PER-SEC",
      "http://qudt.org/vocab/unit/J-PER-CentiM2",
      "http://qudt.org/vocab/unit/K-PER-SEC",
      "http://qudt.org/vocab/unit/BTU_IT-PER-LB-DEG_F",
      "http://qudt.org/vocab/unit/CubanPeso",
      "http://qudt.org/vocab/unit/GAL_US-PER-DAY",
      "http://qudt.org/vocab/unit/KiloCAL_TH-PER-MIN",
      "http://qudt.org/vocab/unit/CyprusPound",
      "http://qudt.org/vocab/unit/BTU_IT-PER-MOL-DEG_F",
      "http://qudt.org/vocab/unit/A-PER-RAD",
      "http://qudt.org/vocab/unit/PicoPA-PER-KiloM",
      "http://qudt.org/vocab/unit/M2-PER-V-SEC",
      "http://qudt.org/vocab/unit/Cedi",
      "http://qudt.org/vocab/unit/MilliBAR-L-PER-SEC",
      "http://qudt.org/vocab/unit/W",
      "http://qudt.org/vocab/unit/S_Ab",
      "http://qudt.org/vocab/unit/VenezuelanBolvar",
      "http://qudt.org/vocab/unit/BTU_TH-FT-PER-HR-FT2-DEG_F",
      "http://qudt.org/vocab/unit/OCT",
      "http://qudt.org/vocab/unit/Ngultrum",
      "http://qudt.org/vocab/unit/BBD",
      "http://qudt.org/vocab/unit/LB-MOL-DEG_F",
      "http://qudt.org/vocab/unit/MI3",
      "http://qudt.org/vocab/unit/MicroS-PER-M",
      "http://qudt.org/vocab/unit/KiloBYTE",
      "http://qudt.org/vocab/unit/N-PER-RAD",
      "http://qudt.org/vocab/unit/MegaHZ-M",
      "http://qudt.org/vocab/unit/FT2",
      "http://qudt.org/vocab/unit/MilliPA",
      "http://qudt.org/vocab/unit/Da",
      "http://qudt.org/vocab/unit/OHM_Stat",
      "http://qudt.org/vocab/unit/NUM-PER-SEC",
      "http://qudt.org/vocab/unit/J-SEC-PER-MOL",
      "http://qudt.org/vocab/unit/MilliN-PER-M",
      "http://qudt.org/vocab/unit/DeciM3-PER-MIN",
      "http://qudt.org/vocab/unit/UnidadDeValorReal",
      "http://qudt.org/vocab/unit/UzbekistanSom",
      "http://qudt.org/vocab/unit/Rufiyaa",
      "http://qudt.org/vocab/unit/YR_Sidereal",
      "http://qudt.org/vocab/unit/KiloLB_F-PER-IN2",
      "http://qudt.org/vocab/unit/MicroC",
      "http://qudt.org/vocab/unit/L-PER-MicroMOL",
      "http://qudt.org/vocab/unit/MegaJ-PER-K",
      "http://qudt.org/vocab/unit/V_Ab-SEC",
      "http://qudt.org/vocab/unit/MegaC-PER-M3",
      "http://qudt.org/vocab/unit/QT_UK-PER-HR",
      "http://qudt.org/vocab/unit/MilliMOL-PER-L",
      "http://qudt.org/vocab/unit/PA-M-PER-SEC2",
      "http://qudt.org/vocab/unit/NAT",
      "http://qudt.org/vocab/unit/TORR",
      "http://qudt.org/vocab/unit/C",
      "http://qudt.org/vocab/unit/MilliGM-PER-DeciL",
      "http://qudt.org/vocab/unit/KiloGM-PER-M2-SEC",
      "http://qudt.org/vocab/unit/TeraOHM",
      "http://qudt.org/vocab/unit/FT2-SEC-DEG_F",
      "http://qudt.org/vocab/unit/OZ-PER-YD3",
      "http://qudt.org/vocab/unit/LB-PER-SEC",
      "http://qudt.org/vocab/unit/DZD",
      "http://qudt.org/vocab/unit/Pataca",
      "http://qudt.org/vocab/unit/MicroPOISE",
      "http://qudt.org/vocab/unit/DEGREE_OECHSLE",
      "http://qudt.org/vocab/unit/NanoW",
      "http://qudt.org/vocab/unit/KiloGM_F-M",
      "http://qudt.org/vocab/unit/WB-M",
      "http://qudt.org/vocab/unit/SEC-FT2",
      "http://qudt.org/vocab/unit/YD3-PER-HR",
      "http://qudt.org/vocab/unit/DEG",
      "http://qudt.org/vocab/unit/MegaPA-M3-PER-SEC",
      "http://qudt.org/vocab/unit/PicoSEC",
      "http://qudt.org/vocab/unit/PER-PlanckMass2",
      "http://qudt.org/vocab/unit/MOL-PER-M2-DAY",
      "http://qudt.org/vocab/unit/GigaOHM",
      "http://qudt.org/vocab/unit/TSP",
      "http://qudt.org/vocab/unit/KiloHZ",
      "http://qudt.org/vocab/unit/CD-PER-IN2",
      "http://qudt.org/vocab/unit/CAL_TH-PER-GM",
      "http://qudt.org/vocab/unit/Gs",
      "http://qudt.org/vocab/unit/FT-LB_F-PER-M2",
      "http://qudt.org/vocab/unit/XOF",
      "http://qudt.org/vocab/unit/K-PER-W",
      "http://qudt.org/vocab/unit/CzechKoruna",
      "http://qudt.org/vocab/unit/EuropeanCompositeUnit",
      "http://qudt.org/vocab/unit/PicoMOL-PER-L-DAY",
      "http://qudt.org/vocab/unit/KiloMOL-PER-M3",
      "http://qudt.org/vocab/unit/V-PER-M",
      "http://qudt.org/vocab/unit/MilliM2",
      "http://qudt.org/vocab/unit/MilliW-PER-CentiM2-MicroM-SR",
      "http://qudt.org/vocab/unit/KiloW-HR",
      "http://qudt.org/vocab/unit/BTU_TH-PER-LB-DEG_F",
      "http://qudt.org/vocab/unit/W-PER-IN2",
      "http://qudt.org/vocab/unit/MicroBQ-PER-L",
      "http://qudt.org/vocab/unit/MicroN",
      "http://qudt.org/vocab/unit/LB-DEG_R",
      "http://qudt.org/vocab/unit/MI_N-PER-HR",
      "http://qudt.org/vocab/unit/MilliBAR-PER-K",
      "http://qudt.org/vocab/unit/NanoMOL-PER-MicroGM-HR",
      "http://qudt.org/vocab/unit/BU_US_DRY-PER-HR",
      "http://qudt.org/vocab/unit/LM",
      "http://qudt.org/vocab/unit/HZ-PER-V",
      "http://qudt.org/vocab/unit/NanoMOL-PER-CentiM3-HR",
      "http://qudt.org/vocab/unit/VietnameseDong",
      "http://qudt.org/vocab/unit/MicroSV-PER-HR",
      "http://qudt.org/vocab/unit/T_Ab",
      "http://qudt.org/vocab/unit/J-M2-PER-KiloGM",
      "http://qudt.org/vocab/unit/JamaicanDollar",
      "http://qudt.org/vocab/unit/YR",
      "http://qudt.org/vocab/unit/C-PER-M2",
      "http://qudt.org/vocab/unit/CAL_TH-PER-G",
      "http://qudt.org/vocab/unit/MilliL",
      "http://qudt.org/vocab/unit/PERCENT",
      "http://qudt.org/vocab/unit/GM-PER-CentiM3",
      "http://qudt.org/vocab/unit/PERMEABILITY_EM_REL",
      "http://qudt.org/vocab/unit/SamoanTala",
      "http://qudt.org/vocab/unit/M2",
      "http://qudt.org/vocab/unit/DEG_F-PER-MIN",
      "http://qudt.org/vocab/unit/MegaGM-PER-M3",
      "http://qudt.org/vocab/unit/GM_Carbon-PER-M2-DAY",
      "http://qudt.org/vocab/unit/HP-PER-M",
      "http://qudt.org/vocab/unit/ColombianPeso",
      "http://qudt.org/vocab/unit/ARE",
      "http://qudt.org/vocab/unit/BU_UK-PER-SEC",
      "http://qudt.org/vocab/unit/KiloGM-PER-MOL",
      "http://qudt.org/vocab/unit/MilliGAL",
      "http://qudt.org/vocab/unit/WB-PER-MilliM",
      "http://qudt.org/vocab/unit/ERG-PER-CentiM2-SEC",
      "http://qudt.org/vocab/unit/DEGREE_BAUME",
      "http://qudt.org/vocab/unit/PER-CentiM3",
      "http://qudt.org/vocab/unit/KiloCAL_IT-PER-HR-M-DEG_C",
      "http://qudt.org/vocab/unit/PER-SEC-M2-SR",
      "http://qudt.org/vocab/unit/CentiM_H2O",
      "http://qudt.org/vocab/unit/MicroFARAD-PER-M",
      "http://qudt.org/vocab/unit/KiloCAL-PER-CentiM2-SEC",
      "http://qudt.org/vocab/unit/PlanckCharge",
      "http://qudt.org/vocab/unit/DEG_F-HR-PER-BTU_IT",
      "http://qudt.org/vocab/unit/LB-PER-FT-HR",
      "http://qudt.org/vocab/unit/PER-M-SEC",
      "http://qudt.org/vocab/unit/OZ-PER-HR",
      "http://qudt.org/vocab/unit/BARAD",
      "http://qudt.org/vocab/unit/KiloPA-M2-PER-GM",
      "http://qudt.org/vocab/unit/PicoM",
      "http://qudt.org/vocab/unit/Somoni",
      "http://qudt.org/vocab/unit/NUM-PER-HectoGM",
      "http://qudt.org/vocab/unit/MegaPA-PER-K",
      "http://qudt.org/vocab/unit/MOL-K",
      "http://qudt.org/vocab/unit/QT_US_DRY",
      "http://qudt.org/vocab/unit/KiloGM-PER-SEC2",
      "http://qudt.org/vocab/unit/MicroW",
      "http://qudt.org/vocab/unit/MegaV",
      "http://qudt.org/vocab/unit/Kina",
      "http://qudt.org/vocab/unit/OZ_VOL_US",
      "http://qudt.org/vocab/unit/W-SEC-PER-M2",
      "http://qudt.org/vocab/unit/BBL_US_PET-PER-HR",
      "http://qudt.org/vocab/unit/KiloGM-M-PER-SEC",
      "http://qudt.org/vocab/unit/MilliV",
      "http://qudt.org/vocab/unit/EarthMass",
      "http://qudt.org/vocab/unit/Tenge",
      "http://qudt.org/vocab/unit/MicroC-PER-M2",
      "http://qudt.org/vocab/unit/Silver-OunceTroy",
      "http://qudt.org/vocab/unit/MilliMOL-PER-MOL",
      "http://qudt.org/vocab/unit/PER-MO",
      "http://qudt.org/vocab/unit/TBSP",
      "http://qudt.org/vocab/unit/REV-PER-SEC2",
      "http://qudt.org/vocab/unit/W-PER-M2-M-SR",
      "http://qudt.org/vocab/unit/IN3",
      "http://qudt.org/vocab/unit/Flight",
      "http://qudt.org/vocab/unit/NTU",
      "http://qudt.org/vocab/unit/BTU_IT-IN-PER-HR-FT2-DEG_F",
      "http://qudt.org/vocab/unit/ChileanPeso",
      "http://qudt.org/vocab/unit/LB-PER-IN2",
      "http://qudt.org/vocab/unit/KiloBIT-PER-SEC",
      "http://qudt.org/vocab/unit/PlanckVolume",
      "http://qudt.org/vocab/unit/DeciN-M",
      "http://qudt.org/vocab/unit/M3-PER-KiloGM-SEC2",
      "http://qudt.org/vocab/unit/GM-PER-KiloGM",
      "http://qudt.org/vocab/unit/ARS",
      "http://qudt.org/vocab/unit/OZ_VOL_US-PER-SEC",
      "http://qudt.org/vocab/unit/USDollar-NextDay",
      "http://qudt.org/vocab/unit/OERSTED-CentiM",
      "http://qudt.org/vocab/unit/CAL_TH",
      "http://qudt.org/vocab/unit/PlanckArea",
      "http://qudt.org/vocab/unit/J-M2",
      "http://qudt.org/vocab/unit/KiloEV",
      "http://qudt.org/vocab/unit/KiloGM-PER-KiloM2",
      "http://qudt.org/vocab/unit/MOL-PER-MIN",
      "http://qudt.org/vocab/unit/M2-HR-DEG_C-PER-KiloCAL_IT",
      "http://qudt.org/vocab/unit/NanoGM-PER-KiloGM",
      "http://qudt.org/vocab/unit/DIOPTER",
      "http://qudt.org/vocab/unit/SerbianDinar",
      "http://qudt.org/vocab/unit/PINT_UK-PER-SEC",
      "http://qudt.org/vocab/unit/TeraC",
      "http://qudt.org/vocab/unit/N-PER-M2",
      "http://qudt.org/vocab/unit/K-M2-PER-KiloGM-SEC",
      "http://qudt.org/vocab/unit/LB-PER-IN3",
      "http://qudt.org/vocab/unit/NanoGM-PER-MicroL",
      "http://qudt.org/vocab/unit/CAL_IT-PER-GM-K",
      "http://qudt.org/vocab/unit/M-KiloGM",
      "http://qudt.org/vocab/unit/MegaV-A_Reactive-HR",
      "http://qudt.org/vocab/unit/MicroM3-PER-M3",
      "http://qudt.org/vocab/unit/KuwaitiDinar",
      "http://qudt.org/vocab/unit/N-M2-PER-KiloGM2",
      "http://qudt.org/vocab/unit/KiloN",
      "http://qudt.org/vocab/unit/MicroFARAD",
      "http://qudt.org/vocab/unit/DeciM3-PER-HR",
      "http://qudt.org/vocab/unit/PER-SEC",
      "http://qudt.org/vocab/unit/THM_EEC",
      "http://qudt.org/vocab/unit/BTU_IT-IN",
      "http://qudt.org/vocab/unit/MegaEV-FemtoM",
      "http://qudt.org/vocab/unit/BTU_IT-PER-LB-MOL",
      "http://qudt.org/vocab/unit/C-PER-MilliM3",
      "http://qudt.org/vocab/unit/MilliGM-PER-M",
      "http://qudt.org/vocab/unit/N-CentiM",
      "http://qudt.org/vocab/unit/RwandaFranc",
      "http://qudt.org/vocab/unit/DEG_C-PER-YR",
      "http://qudt.org/vocab/unit/PINT_UK",
      "http://qudt.org/vocab/unit/KiloCAL-PER-MOL",
      "http://qudt.org/vocab/unit/V-M",
      "http://qudt.org/vocab/unit/RAD-PER-M",
      "http://qudt.org/vocab/unit/GM-PER-MilliM",
      "http://qudt.org/vocab/unit/Quetzal",
      "http://qudt.org/vocab/unit/BBL_UK_PET-PER-DAY",
      "http://qudt.org/vocab/unit/YD3",
      "http://qudt.org/vocab/unit/OERSTED",
      "http://qudt.org/vocab/unit/GAL_UK-PER-DAY",
      "http://qudt.org/vocab/unit/KiloGM-SEC2",
      "http://qudt.org/vocab/unit/NUM-PER-YR",
      "http://qudt.org/vocab/unit/DEG-PER-HR",
      "http://qudt.org/vocab/unit/J-PER-M3-K",
      "http://qudt.org/vocab/unit/DEG-PER-SEC",
      "http://qudt.org/vocab/unit/SolomonIslandsDollar",
      "http://qudt.org/vocab/unit/SEC",
      "http://qudt.org/vocab/unit/MegaBQ",
      "http://qudt.org/vocab/unit/LUX-HR",
      "http://qudt.org/vocab/unit/A-HR",
      "http://qudt.org/vocab/unit/MexicanPeso",
      "http://qudt.org/vocab/unit/U",
      "http://qudt.org/vocab/unit/MIN_Angle",
      "http://qudt.org/vocab/unit/OHM",
      "http://qudt.org/vocab/unit/CentiM2-SEC",
      "http://qudt.org/vocab/unit/DYN",
      "http://qudt.org/vocab/unit/MilliM-PER-MIN",
      "http://qudt.org/vocab/unit/TeraJ",
      "http://qudt.org/vocab/unit/FemtoJ",
      "http://qudt.org/vocab/unit/BU_UK",
      "http://qudt.org/vocab/unit/LB_F-SEC-PER-FT2",
      "http://qudt.org/vocab/unit/V-A_Reactive",
      "http://qudt.org/vocab/unit/MilliW-PER-M2-NanoM",
      "http://qudt.org/vocab/unit/OmaniRial",
      "http://qudt.org/vocab/unit/GM-PER-M2-DAY",
      "http://qudt.org/vocab/unit/PicoMOL-PER-M3",
      "http://qudt.org/vocab/unit/BBL_US_PET-PER-SEC",
      "http://qudt.org/vocab/unit/MicroM-PER-N",
      "http://qudt.org/vocab/unit/PER-PicoM",
      "http://qudt.org/vocab/unit/FARAD",
      "http://qudt.org/vocab/unit/MOL-PER-HR",
      "http://qudt.org/vocab/unit/FT-LA",
      "http://qudt.org/vocab/unit/KiloGM-PER-CentiM3",
      "http://qudt.org/vocab/unit/C-M2-PER-V",
      "http://qudt.org/vocab/unit/MicroMOL-PER-M2-DAY",
      "http://qudt.org/vocab/unit/PSI-M3-PER-SEC",
      "http://qudt.org/vocab/unit/UNITLESS",
      "http://qudt.org/vocab/unit/KiloCAL_TH-PER-SEC",
      "http://qudt.org/vocab/unit/M2-PER-SEC2",
      "http://qudt.org/vocab/unit/OZ_VOL_UK-PER-MIN",
      "http://qudt.org/vocab/unit/MicroV",
      "http://qudt.org/vocab/unit/YD3-PER-DEG_F",
      "http://qudt.org/vocab/unit/TON_Metric-PER-MIN",
      "http://qudt.org/vocab/unit/FalklandIslandsPound",
      "http://qudt.org/vocab/unit/NUM-PER-MilliGM",
      "http://qudt.org/vocab/unit/N-M-SEC-PER-M",
      "http://qudt.org/vocab/unit/DeciB",
      "http://qudt.org/vocab/unit/PER-MicroMOL-L",
      "http://qudt.org/vocab/unit/GM-PER-M",
      "http://qudt.org/vocab/unit/N-M-SEC",
      "http://qudt.org/vocab/unit/TONNE",
      "http://qudt.org/vocab/unit/CH",
      "http://qudt.org/vocab/unit/KiloOHM",
      "http://qudt.org/vocab/unit/PINT_US_DRY",
      "http://qudt.org/vocab/unit/KiloC-PER-M3",
      "http://qudt.org/vocab/unit/PicoH",
      "http://qudt.org/vocab/unit/KiloGM_F",
      "http://qudt.org/vocab/unit/MO_Synodic",
      "http://qudt.org/vocab/unit/GigaPA",
      "http://qudt.org/vocab/unit/NewZealandDollar",
      "http://qudt.org/vocab/unit/OHM-M2-PER-M",
      "http://qudt.org/vocab/unit/DjiboutiFranc",
      "http://qudt.org/vocab/unit/C_Ab-PER-CentiM2",
      "http://qudt.org/vocab/unit/Lilangeni",
      "http://qudt.org/vocab/unit/PicoGM",
      "http://qudt.org/vocab/unit/MilliL-PER-M3",
      "http://qudt.org/vocab/unit/NanoM2",
      "http://qudt.org/vocab/unit/YD-PER-DEG_F",
      "http://qudt.org/vocab/unit/LB_F-PER-FT2",
      "http://qudt.org/vocab/unit/ZeptoC",
      "http://qudt.org/vocab/unit/TON_UK-PER-DAY",
      "http://qudt.org/vocab/unit/J-PER-T2",
      "http://qudt.org/vocab/unit/HP_Brake",
      "http://qudt.org/vocab/unit/KiloGM-PER-MIN",
      "http://qudt.org/vocab/unit/M2-HZ2",
      "http://qudt.org/vocab/unit/PlanckCurrent",
      "http://qudt.org/vocab/unit/PicoW",
      "http://qudt.org/vocab/unit/NanoMOL-PER-KiloGM",
      "http://qudt.org/vocab/unit/FT2-HR-DEG_F",
      "http://qudt.org/vocab/unit/KiloGM-PER-M-SEC2",
      "http://qudt.org/vocab/unit/PER-ANGSTROM",
      "http://qudt.org/vocab/unit/MI_N",
      "http://qudt.org/vocab/unit/TON_Metric-PER-HA",
      "http://qudt.org/vocab/unit/GigaBQ",
      "http://qudt.org/vocab/unit/K-M",
      "http://qudt.org/vocab/unit/YD3-PER-SEC",
      "http://qudt.org/vocab/unit/RAD-PER-MIN",
      "http://qudt.org/vocab/unit/MI-PER-HR",
      "http://qudt.org/vocab/unit/QT_US-PER-MIN",
      "http://qudt.org/vocab/unit/V_Ab",
      "http://qudt.org/vocab/unit/WIRFranc",
      "http://qudt.org/vocab/unit/SLUG-PER-FT3",
      "http://qudt.org/vocab/unit/TebiBYTE",
      "http://qudt.org/vocab/unit/J-PER-M3",
      "http://qudt.org/vocab/unit/MilliM",
      "http://qudt.org/vocab/unit/GI_UK-PER-HR",
      "http://qudt.org/vocab/unit/KiloJ",
      "http://qudt.org/vocab/unit/AFN",
      "http://qudt.org/vocab/unit/NanoM",
      "http://qudt.org/vocab/unit/PlanckFrequency",
      "http://qudt.org/vocab/unit/FemtoMOL-PER-KiloGM",
      "http://qudt.org/vocab/unit/N-PER-MilliM2",
      "http://qudt.org/vocab/unit/GM-PER-MIN",
      "http://qudt.org/vocab/unit/HP_Electric",
      "http://qudt.org/vocab/unit/GI",
      "http://qudt.org/vocab/unit/FARAD_Ab",
      "http://qudt.org/vocab/unit/NanoC",
      "http://qudt.org/vocab/unit/BTU_IT-PER-HR-FT2",
      "http://qudt.org/vocab/unit/M2-PER-SR-J",
      "http://qudt.org/vocab/unit/KiloGM-PER-KiloGM",
      "http://qudt.org/vocab/unit/J-PER-GM",
      "http://qudt.org/vocab/unit/SLUG-PER-FT",
      "http://qudt.org/vocab/unit/Palladium-OunceTroy",
      "http://qudt.org/vocab/unit/CASES-PER-1000I-YR",
      "http://qudt.org/vocab/unit/C-M2",
      "http://qudt.org/vocab/unit/LUX",
      "http://qudt.org/vocab/unit/MegaBIT-PER-SEC",
      "http://qudt.org/vocab/unit/IN_H2O",
      "http://qudt.org/vocab/unit/TON_SHORT",
      "http://qudt.org/vocab/unit/BBL_US-PER-MIN",
      "http://qudt.org/vocab/unit/MicroM2",
      "http://qudt.org/vocab/unit/S",
      "http://qudt.org/vocab/unit/RAD-PER-HR",
      "http://qudt.org/vocab/unit/PER-KiloV-A-HR",
      "http://qudt.org/vocab/unit/QT_UK-PER-MIN",
      "http://qudt.org/vocab/unit/DYN-PER-CentiM2",
      "http://qudt.org/vocab/unit/KiloWB-PER-M",
      "http://qudt.org/vocab/unit/PlanckMass",
      "http://qudt.org/vocab/unit/GRAIN",
      "http://qudt.org/vocab/unit/SlovakKoruna",
      "http://qudt.org/vocab/unit/GAL_US-PER-SEC",
      "http://qudt.org/vocab/unit/C_Stat",
      "http://qudt.org/vocab/unit/Hryvnia",
      "http://qudt.org/vocab/unit/PER-CentiM",
      "http://qudt.org/vocab/unit/LB-PER-M3",
      "http://qudt.org/vocab/unit/GI_US-PER-DAY",
      "http://qudt.org/vocab/unit/KiloCAL-PER-MIN",
      "http://qudt.org/vocab/unit/LB_F-FT",
      "http://qudt.org/vocab/unit/BTU_IT-PER-DEG_F",
      "http://qudt.org/vocab/unit/Kroon",
      "http://qudt.org/vocab/unit/GM_Nitrogen-PER-M2-DAY",
      "http://qudt.org/vocab/unit/KiloCAL-PER-GM",
      "http://qudt.org/vocab/unit/NUM-PER-L",
      "http://qudt.org/vocab/unit/NanoGM-PER-L",
      "http://qudt.org/vocab/unit/MilliBAR-PER-BAR",
      "http://qudt.org/vocab/unit/LB-FT2",
      "http://qudt.org/vocab/unit/FijiDollar",
      "http://qudt.org/vocab/unit/PH",
      "http://qudt.org/vocab/unit/KiloPA-PER-MilliM",
      "http://qudt.org/vocab/unit/BBL_US-PER-DAY",
      "http://qudt.org/vocab/unit/FT3",
      "http://qudt.org/vocab/unit/MO_MeanGREGORIAN",
      "http://qudt.org/vocab/unit/MI-PER-MIN",
      "http://qudt.org/vocab/unit/N-M-PER-M",
      "http://qudt.org/vocab/unit/MilliBAR-M3-PER-SEC",
      "http://qudt.org/vocab/unit/FBM",
      "http://qudt.org/vocab/unit/MilliCi",
      "http://qudt.org/vocab/unit/CentiBAR",
      "http://qudt.org/vocab/unit/A-PER-M",
      "http://qudt.org/vocab/unit/CentiM2",
      "http://qudt.org/vocab/unit/PER-M-NanoM",
      "http://qudt.org/vocab/unit/L-PER-DAY",
      "http://qudt.org/vocab/unit/MillionUSD-PER-YR",
      "http://qudt.org/vocab/unit/BTU_TH",
      "http://qudt.org/vocab/unit/BTU_IT-FT-PER-FT2-HR-DEG_F",
      "http://qudt.org/vocab/unit/YD3-PER-DAY",
      "http://qudt.org/vocab/unit/MilliL-PER-CentiM2-MIN",
      "http://qudt.org/vocab/unit/FT2-PER-SEC",
      "http://qudt.org/vocab/unit/TON_SHORT-PER-HR",
      "http://qudt.org/vocab/unit/MicroGM-PER-GM",
      "http://qudt.org/vocab/unit/BTU_TH-IN-PER-FT2-SEC-DEG_F",
      "http://qudt.org/vocab/unit/PINT_UK-PER-DAY",
      "http://qudt.org/vocab/unit/KiloGM-M2-PER-SEC",
      "http://qudt.org/vocab/unit/PetaBYTE",
      "http://qudt.org/vocab/unit/TunisianDinar",
      "http://qudt.org/vocab/unit/KN-PER-SEC",
      "http://qudt.org/vocab/unit/PicoFARAD-PER-M",
      "http://qudt.org/vocab/unit/RussianRuble",
      "http://qudt.org/vocab/unit/MexicanUnidadDeInversion",
      "http://qudt.org/vocab/unit/HongKongDollar",
      "http://qudt.org/vocab/unit/HaitiGourde",
      "http://qudt.org/vocab/unit/QT_UK",
      "http://qudt.org/vocab/unit/KiloM-PER-HR",
      "http://qudt.org/vocab/unit/OZ-PER-GAL",
      "http://qudt.org/vocab/unit/MilliGM-PER-M3-HR",
      "http://qudt.org/vocab/unit/BTU_IT-PER-LB-DEG_R",
      "http://qudt.org/vocab/unit/PlanckImpedance",
      "http://qudt.org/vocab/unit/KiloN-M",
      "http://qudt.org/vocab/unit/PSI-YD3-PER-SEC",
      "http://qudt.org/vocab/unit/M-K",
      "http://qudt.org/vocab/unit/SLUG",
      "http://qudt.org/vocab/unit/KiloGM-PER-M3",
      "http://qudt.org/vocab/unit/GRAY-PER-SEC",
      "http://qudt.org/vocab/unit/DecaM",
      "http://qudt.org/vocab/unit/MilliGRAY",
      "http://qudt.org/vocab/unit/DEG2",
      "http://qudt.org/vocab/unit/V-A-HR",
      "http://qudt.org/vocab/unit/A-PER-DEG_C",
      "http://qudt.org/vocab/unit/KIP_F",
      "http://qudt.org/vocab/unit/KiloL",
      "http://qudt.org/vocab/unit/GR",
      "http://qudt.org/vocab/unit/TON_US",
      "http://qudt.org/vocab/unit/QT_US-PER-HR",
      "http://qudt.org/vocab/unit/MicroBAR",
      "http://qudt.org/vocab/unit/H_Ab",
      "http://qudt.org/vocab/unit/M2-PER-KiloGM",
      "http://qudt.org/vocab/unit/W-PER-M",
      "http://qudt.org/vocab/unit/SHANNON",
      "http://qudt.org/vocab/unit/IN3-PER-SEC",
      "http://qudt.org/vocab/unit/HP_Metric",
      "http://qudt.org/vocab/unit/CAL_TH-PER-CentiM-SEC-DEG_C",
      "http://qudt.org/vocab/unit/DAY_Sidereal",
      "http://qudt.org/vocab/unit/A-PER-CentiM2",
      "http://qudt.org/vocab/unit/PPTH",
      "http://qudt.org/vocab/unit/KiloLB_F-FT-PER-LB",
      "http://qudt.org/vocab/unit/DEG_R-PER-HR",
      "http://qudt.org/vocab/unit/CD-PER-M2",
      "http://qudt.org/vocab/unit/K-PER-HR",
      "http://qudt.org/vocab/unit/KiloHZ-M",
      "http://qudt.org/vocab/unit/GuineaFranc",
      "http://qudt.org/vocab/unit/TEX",
      "http://qudt.org/vocab/unit/Quarter_UK",
      "http://qudt.org/vocab/unit/ATM",
      "http://qudt.org/vocab/unit/DEG_C-WK",
      "http://qudt.org/vocab/unit/PINT",
      "http://qudt.org/vocab/unit/BTU_IT-PER-SEC-FT-DEG_R",
      "http://qudt.org/vocab/unit/HZ-PER-K",
      "http://qudt.org/vocab/unit/PK_US_DRY-PER-HR",
      "http://qudt.org/vocab/unit/MilliPA-SEC-PER-BAR",
      "http://qudt.org/vocab/unit/ComoroFranc",
      "http://qudt.org/vocab/unit/WK",
      "http://qudt.org/vocab/unit/KiloCAL-PER-CentiM2-MIN",
      "http://qudt.org/vocab/unit/IN-PER-DEG_F",
      "http://qudt.org/vocab/unit/Kwanza",
      "http://qudt.org/vocab/unit/W-M2",
      "http://qudt.org/vocab/unit/CentiM2-PER-SEC",
      "http://qudt.org/vocab/unit/V2-PER-K2",
      "http://qudt.org/vocab/unit/HZ-M",
      "http://qudt.org/vocab/unit/SwissFranc",
      "http://qudt.org/vocab/unit/MilliL-PER-M2-DAY",
      "http://qudt.org/vocab/unit/MOL-PER-M2-SEC-SR",
      "http://qudt.org/vocab/unit/MilliGM-PER-L",
      "http://qudt.org/vocab/unit/MicroGM-PER-M3-HR",
      "http://qudt.org/vocab/unit/ERG-PER-GM",
      "http://qudt.org/vocab/unit/TON_SHIPPING_US",
      "http://qudt.org/vocab/unit/BermudaDollar",
      "http://qudt.org/vocab/unit/FT3-PER-SEC",
      "http://qudt.org/vocab/unit/LB-PER-GAL",
      "http://qudt.org/vocab/unit/C-PER-MilliM2",
      "http://qudt.org/vocab/unit/KiloA-HR",
      "http://qudt.org/vocab/unit/M2-PER-GM",
      "http://qudt.org/vocab/unit/OZ_F",
      "http://qudt.org/vocab/unit/KiloGM-PER-DeciM3",
      "http://qudt.org/vocab/unit/M3-PER-SEC2",
      "http://qudt.org/vocab/unit/PERCENT-PER-HR",
      "http://qudt.org/vocab/unit/FT",
      "http://qudt.org/vocab/unit/DEG_C-PER-MIN",
      "http://qudt.org/vocab/unit/MI2",
      "http://qudt.org/vocab/unit/HR-FT2",
      "http://qudt.org/vocab/unit/KiloM-PER-DAY",
      "http://qudt.org/vocab/unit/MegaJ-PER-KiloGM",
      "http://qudt.org/vocab/unit/MegaPA-PER-BAR",
      "http://qudt.org/vocab/unit/TONNE-PER-HA",
      "http://qudt.org/vocab/unit/F",
      "http://qudt.org/vocab/unit/BTU_TH-PER-MIN",
      "http://qudt.org/vocab/unit/GigaW-HR",
      "http://qudt.org/vocab/unit/SyrianPound",
      "http://qudt.org/vocab/unit/Tugrik",
      "http://qudt.org/vocab/unit/DEG_F-PER-HR",
      "http://qudt.org/vocab/unit/W-HR",
      "http://qudt.org/vocab/unit/PER-WK",
      "http://qudt.org/vocab/unit/C-PER-KiloGM-SEC",
      "http://qudt.org/vocab/unit/ERG-PER-CentiM",
      "http://qudt.org/vocab/unit/J-PER-MOL",
      "http://qudt.org/vocab/unit/MilliA-PER-MilliM",
      "http://qudt.org/vocab/unit/MilliJ",
      "http://qudt.org/vocab/unit/MIL_Circ",
      "http://qudt.org/vocab/unit/PSI-PER-PSI",
      "http://qudt.org/vocab/unit/OZ_VOL_UK-PER-HR",
      "http://qudt.org/vocab/unit/MI",
      "http://qudt.org/vocab/unit/Debye",
      "http://qudt.org/vocab/unit/BYTE",
      "http://qudt.org/vocab/unit/PicoA-PER-MicroMOL-L",
      "http://qudt.org/vocab/unit/MegaOHM",
      "http://qudt.org/vocab/unit/YoctoC",
      "http://qudt.org/vocab/unit/BBL_UK_PET",
      "http://qudt.org/vocab/unit/BQ",
      "http://qudt.org/vocab/unit/Lek",
      "http://qudt.org/vocab/unit/Loti",
      "http://qudt.org/vocab/unit/BTU_TH-FT-PER-FT2-HR-DEG_F",
      "http://qudt.org/vocab/unit/MilliC-PER-M2",
      "http://qudt.org/vocab/unit/NanoMOL-PER-MicroMOL-DAY",
      "http://qudt.org/vocab/unit/PER-M2",
      "http://qudt.org/vocab/unit/PERCENT-PER-M",
      "http://qudt.org/vocab/unit/GigaHZ",
      "http://qudt.org/vocab/unit/K2",
      "http://qudt.org/vocab/unit/MicroG",
      "http://qudt.org/vocab/unit/SolarMass",
      "http://qudt.org/vocab/unit/N-PER-MilliM",
      "http://qudt.org/vocab/unit/DEG_C-PER-SEC",
      "http://qudt.org/vocab/unit/BTU_IT-PER-SEC",
      "http://qudt.org/vocab/unit/MACH",
      "http://qudt.org/vocab/unit/MOL-PER-DeciM3",
      "http://qudt.org/vocab/unit/MilliH-PER-OHM",
      "http://qudt.org/vocab/unit/PoundSterling",
      "http://qudt.org/vocab/unit/OZ-PER-SEC",
      "http://qudt.org/vocab/unit/PetaC",
      "http://qudt.org/vocab/unit/W-PER-M2-SR",
      "http://qudt.org/vocab/unit/GAL_US-PER-MIN",
      "http://qudt.org/vocab/unit/NanoA",
      "http://qudt.org/vocab/unit/AMU",
      "http://qudt.org/vocab/unit/NanoH-PER-M",
      "http://qudt.org/vocab/unit/TonEnergy",
      "http://qudt.org/vocab/unit/ZettaC",
      "http://qudt.org/vocab/unit/RAD-PER-SEC",
      "http://qudt.org/vocab/unit/Forint",
      "http://qudt.org/vocab/unit/GAUGE_FR",
      "http://qudt.org/vocab/unit/TON_US-PER-YD3",
      "http://qudt.org/vocab/unit/FARAD-PER-M",
      "http://qudt.org/vocab/unit/W-PER-M2-NanoM-SR",
      "http://qudt.org/vocab/unit/GRAD",
      "http://qudt.org/vocab/unit/PER-M2-SEC",
      "http://qudt.org/vocab/unit/MIN",
      "http://qudt.org/vocab/unit/MegaV-PER-M",
      "http://qudt.org/vocab/unit/NUM-PER-KiloM2",
      "http://qudt.org/vocab/unit/QatariRial",
      "http://qudt.org/vocab/unit/V-PER-MicroSEC",
      "http://qudt.org/vocab/unit/IN_HG",
      "http://qudt.org/vocab/unit/HZ-PER-T",
      "http://qudt.org/vocab/unit/A-M2-PER-J-SEC",
      "http://qudt.org/vocab/unit/PK_UK-PER-HR",
      "http://qudt.org/vocab/unit/DEATHS-PER-1000I-YR",
      "http://qudt.org/vocab/unit/IN3-PER-HR",
      "http://qudt.org/vocab/unit/REV-PER-HR",
      "http://qudt.org/vocab/unit/QT_US",
      "http://qudt.org/vocab/unit/FT3-PER-HR",
      "http://qudt.org/vocab/unit/NUM-PER-HR",
      "http://qudt.org/vocab/unit/THM_US",
      "http://qudt.org/vocab/unit/CentiM-PER-SEC",
      "http://qudt.org/vocab/unit/CAL_TH-PER-SEC-CentiM2-K",
      "http://qudt.org/vocab/unit/A_Stat",
      "http://qudt.org/vocab/unit/ExaBYTE",
      "http://qudt.org/vocab/unit/FT-LB_F",
      "http://qudt.org/vocab/unit/DeciBAR-PER-YR",
      "http://qudt.org/vocab/unit/NanoT",
      "http://qudt.org/vocab/unit/BulgarianLev",
      "http://qudt.org/vocab/unit/NewTurkishLira",
      "http://qudt.org/vocab/unit/YD2",
      "http://qudt.org/vocab/unit/NanoBQ-PER-L",
      "http://qudt.org/vocab/unit/OZ-PER-GAL_UK",
      "http://qudt.org/vocab/unit/DeciL",
      "http://qudt.org/vocab/unit/FARAD_Stat",
      "http://qudt.org/vocab/unit/LB_F-PER-LB",
      "http://qudt.org/vocab/unit/CentiM3-PER-MOL",
      "http://qudt.org/vocab/unit/FT-PER-MIN",
      "http://qudt.org/vocab/unit/MegaJ",
      "http://qudt.org/vocab/unit/RAD-M2-PER-MOL",
      "http://qudt.org/vocab/unit/AttoFARAD",
      "http://qudt.org/vocab/unit/MegaJ-PER-SEC",
      "http://qudt.org/vocab/unit/FT-LB_F-PER-MIN",
      "http://qudt.org/vocab/unit/NepaleseRupee",
      "http://qudt.org/vocab/unit/CentiL",
      "http://qudt.org/vocab/unit/GM-PER-L",
      "http://qudt.org/vocab/unit/NanoMOL-PER-L-HR",
      "http://qudt.org/vocab/unit/BurundianFranc",
      "http://qudt.org/vocab/unit/PK_UK-PER-DAY",
      "http://qudt.org/vocab/unit/MicroH-PER-KiloOHM",
      "http://qudt.org/vocab/unit/NewIsraeliShekel",
      "http://qudt.org/vocab/unit/BTU_IT-IN-PER-FT2-SEC-DEG_F",
      "http://qudt.org/vocab/unit/V-PER-MilliM",
      "http://qudt.org/vocab/unit/MilliFARAD",
      "http://qudt.org/vocab/unit/OZ_TROY",
      "http://qudt.org/vocab/unit/KiloGM-MilliM2",
      "http://qudt.org/vocab/unit/FT-PER-HR",
      "http://qudt.org/vocab/unit/BTU_IT",
      "http://qudt.org/vocab/unit/PlanckFrequency_Ang",
      "http://qudt.org/vocab/unit/J-PER-K",
      "http://qudt.org/vocab/unit/SwedishKrona",
      "http://qudt.org/vocab/unit/MilliGM-PER-M3-DAY",
      "http://qudt.org/vocab/unit/FemtoC",
      "http://qudt.org/vocab/unit/GuyanaDollar",
      "http://qudt.org/vocab/unit/LebanesePound",
      "http://qudt.org/vocab/unit/MIL",
      "http://qudt.org/vocab/unit/LB-PER-IN",
      "http://qudt.org/vocab/unit/J-SEC",
      "http://qudt.org/vocab/unit/L-PER-SEC",
      "http://qudt.org/vocab/unit/QT_UK-PER-DAY",
      "http://qudt.org/vocab/unit/FT2-HR-DEG_F-PER-BTU_IT",
      "http://qudt.org/vocab/unit/MilliMOL-PER-M2-DAY",
      "http://qudt.org/vocab/unit/KiloGM-PER-M-SEC",
      "http://qudt.org/vocab/unit/H-PER-KiloOHM",
      "http://qudt.org/vocab/unit/W-PER-M-K",
      "http://qudt.org/vocab/unit/BTU_IT-IN-PER-SEC-FT2-DEG_F",
      "http://qudt.org/vocab/unit/KiloJ-PER-KiloGM",
      "http://qudt.org/vocab/unit/SingaporeDollar",
      "http://qudt.org/vocab/unit/MalaysianRinggit",
      "http://qudt.org/vocab/unit/N-PER-CentiM2",
      "http://qudt.org/vocab/unit/C-M",
      "http://qudt.org/vocab/unit/CAL_IT-PER-GM-DEG_C",
      "http://qudt.org/vocab/unit/PK_US_DRY-PER-SEC",
      "http://qudt.org/vocab/unit/PK_US_DRY-PER-MIN",
      "http://qudt.org/vocab/unit/BTU_IT-PER-SEC-FT2-DEG_R",
      "http://qudt.org/vocab/unit/PERCENT-PER-WK",
      "http://qudt.org/vocab/unit/RAD-M2-PER-KiloGM",
      "http://qudt.org/vocab/unit/DeciM3",
      "http://qudt.org/vocab/unit/KiloGM-PER-HA",
      "http://qudt.org/vocab/unit/CentiGM",
      "http://qudt.org/vocab/unit/K-PER-T",
      "http://qudt.org/vocab/unit/DECADE",
      "http://qudt.org/vocab/unit/GibraltarPound",
      "http://qudt.org/vocab/unit/J-M-PER-MOL",
      "http://qudt.org/vocab/unit/N-SEC-PER-RAD",
      "http://qudt.org/vocab/unit/BQ-PER-KiloGM",
      "http://qudt.org/vocab/unit/MegaW",
      "http://qudt.org/vocab/unit/GAUSS",
      "http://qudt.org/vocab/unit/CentiM3",
      "http://qudt.org/vocab/unit/CUP_US",
      "http://qudt.org/vocab/unit/MilliG",
      "http://qudt.org/vocab/unit/KiloCAL",
      "http://qudt.org/vocab/unit/FT-LB_F-PER-FT2",
      "http://qudt.org/vocab/unit/KiloGM2-PER-SEC2",
      "http://qudt.org/vocab/unit/BIOT",
      "http://qudt.org/vocab/unit/G",
      "http://qudt.org/vocab/unit/M2-PER-SR",
      "http://qudt.org/vocab/unit/MegaW-HR",
      "http://qudt.org/vocab/unit/DeciTONNE",
      "http://qudt.org/vocab/unit/MillionUSD",
      "http://qudt.org/vocab/unit/CP",
      "http://qudt.org/vocab/unit/BTU_IT-FT",
      "http://qudt.org/vocab/unit/PER-YR",
      "http://qudt.org/vocab/unit/MilliM4",
      "http://qudt.org/vocab/unit/Platinum-OunceTroy",
      "http://qudt.org/vocab/unit/THB",
      "http://qudt.org/vocab/unit/TON_LONG-PER-YD3",
      "http://qudt.org/vocab/unit/KiloJ-PER-K",
      "http://qudt.org/vocab/unit/GM-MilliM",
      "http://qudt.org/vocab/unit/A",
      "http://qudt.org/vocab/unit/MegaV-A",
      "http://qudt.org/vocab/unit/BTU_TH-PER-FT3",
      "http://qudt.org/vocab/unit/MicroL-PER-L",
      "http://qudt.org/vocab/unit/PINT_US-PER-HR",
      "http://qudt.org/vocab/unit/MilliL-PER-SEC",
      "http://qudt.org/vocab/unit/SV",
      "http://qudt.org/vocab/unit/M4-PER-SEC",
      "http://qudt.org/vocab/unit/M3-PER-K",
      "http://qudt.org/vocab/unit/CAL_IT-PER-SEC-CentiM-K",
      "http://qudt.org/vocab/unit/MilliN",
      "http://qudt.org/vocab/unit/TON_Metric-PER-HR",
      "http://qudt.org/vocab/unit/KiloCAL-PER-SEC",
      "http://qudt.org/vocab/unit/SUSCEPTIBILITY_MAG",
      "http://qudt.org/vocab/unit/BBL_UK_PET-PER-HR",
      "http://qudt.org/vocab/unit/NanoS-PER-CentiM",
      "http://qudt.org/vocab/unit/QT_US-PER-SEC",
      "http://qudt.org/vocab/unit/FT3-PER-DAY",
      "http://qudt.org/vocab/unit/MilliW",
      "http://qudt.org/vocab/unit/MicroMOL-PER-L",
      "http://qudt.org/vocab/unit/MauritiusRupee",
      "http://qudt.org/vocab/unit/EgyptianPound",
      "http://qudt.org/vocab/unit/BTU_IT-PER-FT2-HR-DEG_F",
      "http://qudt.org/vocab/unit/MicroH",
      "http://qudt.org/vocab/unit/LB-PER-HR",
      "http://qudt.org/vocab/unit/W-M2-PER-SR",
      "http://qudt.org/vocab/unit/HectoC",
      "http://qudt.org/vocab/unit/MilliM-PER-K",
      "http://qudt.org/vocab/unit/FT2-DEG_F",
      "http://qudt.org/vocab/unit/M-PER-FARAD",
      "http://qudt.org/vocab/unit/Ouguiya",
      "http://qudt.org/vocab/unit/DeciBAR",
      "http://qudt.org/vocab/unit/M3-PER-HR",
      "http://qudt.org/vocab/unit/MilliPA-SEC",
      "http://qudt.org/vocab/unit/FT-LB_F-PER-FT2-SEC",
      "http://qudt.org/vocab/unit/GI_US-PER-MIN",
      "http://qudt.org/vocab/unit/PlanckCurrentDensity",
      "http://qudt.org/vocab/unit/DEGREE_TWADDELL",
      "http://qudt.org/vocab/unit/MicroATM",
      "http://qudt.org/vocab/unit/PER-MIN",
      "http://qudt.org/vocab/unit/MOL-PER-L",
      "http://qudt.org/vocab/unit/MilliR_man",
      "http://qudt.org/vocab/unit/FT3-PER-MIN",
      "http://qudt.org/vocab/unit/K-SEC",
      "http://qudt.org/vocab/unit/M-PER-K",
      "http://qudt.org/vocab/unit/KiloGM-PER-SEC",
      "http://qudt.org/vocab/unit/H",
      "http://qudt.org/vocab/unit/V-PER-IN",
      "http://qudt.org/vocab/unit/PlanckTemperature",
      "http://qudt.org/vocab/unit/KiloM-PER-SEC",
      "http://qudt.org/vocab/unit/W-PER-SR",
      "http://qudt.org/vocab/unit/HectoBAR",
      "http://qudt.org/vocab/unit/CentiM3-PER-CentiM3",
      "http://qudt.org/vocab/unit/DEGREE_BAUME_US_HEAVY",
      "http://qudt.org/vocab/unit/BU_US_DRY-PER-MIN",
      "http://qudt.org/vocab/unit/BTU_TH-PER-LB",
      "http://qudt.org/vocab/unit/MegaHZ-PER-T",
      "http://qudt.org/vocab/unit/MegaBAR",
      "http://qudt.org/vocab/unit/BU_US_DRY-PER-SEC",
      "http://qudt.org/vocab/unit/OZ_VOL_US-PER-HR",
      "http://qudt.org/vocab/unit/MilliM3",
      "http://qudt.org/vocab/unit/KiloC",
      "http://qudt.org/vocab/unit/MicroCi",
      "http://qudt.org/vocab/unit/M-PER-MIN",
      "http://qudt.org/vocab/unit/GON",
      "http://qudt.org/vocab/unit/FARAD_Ab-PER-CentiM",
      "http://qudt.org/vocab/unit/MilliM2-PER-SEC",
      "http://qudt.org/vocab/unit/OZ_VOL_US-PER-MIN",
      "http://qudt.org/vocab/unit/CentiM3-PER-M3",
      "http://qudt.org/vocab/unit/DeciM3-PER-MOL",
      "http://qudt.org/vocab/unit/CentiM-PER-HR",
      "http://qudt.org/vocab/unit/BAN",
      "http://qudt.org/vocab/unit/KiloL-PER-HR",
      "http://qudt.org/vocab/unit/KiloBQ",
      "http://qudt.org/vocab/unit/LB_F-PER-IN2",
      "http://qudt.org/vocab/unit/GM-PER-CentiM2-YR",
      "http://qudt.org/vocab/unit/TON_SHORT-PER-YD3",
      "http://qudt.org/vocab/unit/ERG-SEC",
      "http://qudt.org/vocab/unit/GRAIN-PER-GAL",
      "http://qudt.org/vocab/unit/KiloGM_F-M-PER-SEC",
      "http://qudt.org/vocab/unit/PlanckPower",
      "http://qudt.org/vocab/unit/DEG_C-KiloGM-PER-M2",
      "http://qudt.org/vocab/unit/MicroMOL-PER-L-HR",
      "http://qudt.org/vocab/unit/MO",
      "http://qudt.org/vocab/unit/MegaL",
      "http://qudt.org/vocab/unit/GigaJ",
      "http://qudt.org/vocab/unit/LB_F-SEC-PER-IN2",
      "http://qudt.org/vocab/unit/M3-PER-MOL",
      "http://qudt.org/vocab/unit/LB_F-PER-IN2-SEC",
      "http://qudt.org/vocab/unit/TON_Metric-PER-SEC",
      "http://qudt.org/vocab/unit/BU_US",
      "http://qudt.org/vocab/unit/M2-HZ",
      "http://qudt.org/vocab/unit/N-M-PER-KiloGM",
      "http://qudt.org/vocab/unit/FT2-PER-BTU_IT-IN",
      "http://qudt.org/vocab/unit/NanoMOL-PER-L-DAY",
      "http://qudt.org/vocab/unit/NUM",
      "http://qudt.org/vocab/unit/PetaJ",
      "http://qudt.org/vocab/unit/MilliMOL-PER-GM",
      "http://qudt.org/vocab/unit/SaudiRiyal",
      "http://qudt.org/vocab/unit/Boliviano",
      "http://qudt.org/vocab/unit/HectoPA-M3-PER-SEC",
      "http://qudt.org/vocab/unit/FemtoGM-PER-L",
      "http://qudt.org/vocab/unit/MegaYR",
      "http://qudt.org/vocab/unit/MicroM-PER-L-DAY",
      "http://qudt.org/vocab/unit/Guarani",
      "http://qudt.org/vocab/unit/M2-PER-HZ-DEG",
      "http://qudt.org/vocab/unit/MOL-PER-MOL",
      "http://qudt.org/vocab/unit/GAL_UK-PER-MIN",
      "http://qudt.org/vocab/unit/SomaliShilling",
      "http://qudt.org/vocab/unit/PER-M",
      "http://qudt.org/vocab/unit/ExaC",
      "http://qudt.org/vocab/unit/DEG_F",
      "http://qudt.org/vocab/unit/MilliM_HGA",
      "http://qudt.org/vocab/unit/PER-MilliM",
      "http://qudt.org/vocab/unit/V-PER-M2",
      "http://qudt.org/vocab/unit/MicroMOL",
      "http://qudt.org/vocab/unit/CentiM_HG",
      "http://qudt.org/vocab/unit/DeciM",
      "http://qudt.org/vocab/unit/BSD",
      "http://qudt.org/vocab/unit/IN3-PER-MIN",
      "http://qudt.org/vocab/unit/KiloP",
      "http://qudt.org/vocab/unit/L-PER-HR",
      "http://qudt.org/vocab/unit/KiloTON_Metric",
      "http://qudt.org/vocab/unit/Denar",
      "http://qudt.org/vocab/unit/MegaBYTE",
      "http://qudt.org/vocab/unit/MegaPA",
      "http://qudt.org/vocab/unit/H_Stat-PER-CentiM",
      "http://qudt.org/vocab/unit/C-PER-M",
      "http://qudt.org/vocab/unit/PPB",
      "http://qudt.org/vocab/unit/MegaN-M",
      "http://qudt.org/vocab/unit/PDL",
      "http://qudt.org/vocab/unit/PER-M3",
      "http://qudt.org/vocab/unit/MicroSEC",
      "http://qudt.org/vocab/unit/KN",
      "http://qudt.org/vocab/unit/GM-PER-KiloM",
      "http://qudt.org/vocab/unit/M-PER-SEC",
      "http://qudt.org/vocab/unit/M2-K-PER-W",
      "http://qudt.org/vocab/unit/A_Ab",
      "http://qudt.org/vocab/unit/PicoFARAD",
      "http://qudt.org/vocab/unit/MilliMOL-PER-M2-SEC",
      "http://qudt.org/vocab/unit/TeraW",
      "http://qudt.org/vocab/unit/MilliBAR",
      "http://qudt.org/vocab/unit/DYN-SEC-PER-CentiM3",
      "http://qudt.org/vocab/unit/E",
      "http://qudt.org/vocab/unit/KiloPA",
      "http://qudt.org/vocab/unit/NUM-PER-GM",
      "http://qudt.org/vocab/unit/DEG-PER-SEC2",
      "http://qudt.org/vocab/unit/AC",
      "http://qudt.org/vocab/unit/NuevoSol",
      "http://qudt.org/vocab/unit/DEGREE_BRIX",
      "http://qudt.org/vocab/unit/KiloV",
      "http://qudt.org/vocab/unit/MilliGM-PER-M3-SEC",
      "http://qudt.org/vocab/unit/MicroM3-PER-MilliL",
      "http://qudt.org/vocab/unit/R",
      "http://qudt.org/vocab/unit/A_Ab-CentiM2",
      "http://qudt.org/vocab/unit/HectoM",
      "http://qudt.org/vocab/unit/EV-PER-T",
      "http://qudt.org/vocab/unit/A-PER-CentiM",
      "http://qudt.org/vocab/unit/OZ-PER-GAL_US",
      "http://qudt.org/vocab/unit/PER-T-SEC",
      "http://qudt.org/vocab/unit/NUM-PER-M2",
      "http://qudt.org/vocab/unit/SriLankaRupee",
      "http://qudt.org/vocab/unit/DeciGM",
      "http://qudt.org/vocab/unit/CentiM3-PER-HR",
      "http://qudt.org/vocab/unit/LB_F-PER-IN",
      "http://qudt.org/vocab/unit/DEG_F-PER-K",
      "http://qudt.org/vocab/unit/PER-K",
      "http://qudt.org/vocab/unit/PK_UK-PER-MIN",
      "http://qudt.org/vocab/unit/GM-PER-DeciM3",
      "http://qudt.org/vocab/unit/W-PER-M2-NanoM",
      "http://qudt.org/vocab/unit/MicroGM",
      "http://qudt.org/vocab/unit/PER-YD3",
      "http://qudt.org/vocab/unit/CM_H2O",
      "http://qudt.org/vocab/unit/BQ-PER-L",
      "http://qudt.org/vocab/unit/KiloEV-PER-MicroM",
      "http://qudt.org/vocab/unit/OZ_VOL_US-PER-DAY",
      "http://qudt.org/vocab/unit/YuanRenminbi",
      "http://qudt.org/vocab/unit/PER-BAR",
      "http://qudt.org/vocab/unit/NanoMOL-PER-M2-DAY",
      "http://qudt.org/vocab/unit/MicroM-PER-K",
      "http://qudt.org/vocab/unit/MI_US",
      "http://qudt.org/vocab/unit/OZ-PER-MIN",
      "http://qudt.org/vocab/unit/SaintHelenaPound",
      "http://qudt.org/vocab/unit/OHM_Ab",
      "http://qudt.org/vocab/unit/NAT-PER-SEC",
      "http://qudt.org/vocab/unit/NUM-PER-M2-DAY",
      "http://qudt.org/vocab/unit/MilliTORR",
      "http://qudt.org/vocab/unit/PER-IN3",
      "http://qudt.org/vocab/unit/PER-SR",
      "http://qudt.org/vocab/unit/PK_US_DRY",
      "http://qudt.org/vocab/unit/BU_UK-PER-HR",
      "http://qudt.org/vocab/unit/PicoW-PER-CentiM2-L",
      "http://qudt.org/vocab/unit/WB-PER-M",
      "http://qudt.org/vocab/unit/MilliL-PER-KiloGM",
      "http://qudt.org/vocab/unit/USDollar",
      "http://qudt.org/vocab/unit/MOL-PER-M2-SEC",
      "http://qudt.org/vocab/unit/C4-M4-PER-J3",
      "http://qudt.org/vocab/unit/MilliN-M",
      "http://qudt.org/vocab/unit/N-SEC-PER-M3",
      "http://qudt.org/vocab/unit/LiberianDollar",
      "http://qudt.org/vocab/unit/BTU_IT-PER-LB",
      "http://qudt.org/vocab/unit/W-PER-M2-M",
      "http://qudt.org/vocab/unit/KiloGM_F-PER-M2",
      "http://qudt.org/vocab/unit/MilliGM-PER-GM",
      "http://qudt.org/vocab/unit/PINT_UK-PER-MIN",
      "http://qudt.org/vocab/unit/SeychellesRupee",
      "http://qudt.org/vocab/unit/PicoMOL-PER-M2-DAY",
      "http://qudt.org/vocab/unit/K-M-PER-W",
      "http://qudt.org/vocab/unit/YR_Common",
      "http://qudt.org/vocab/unit/SLUG-PER-SEC",
      "http://qudt.org/vocab/unit/NUM-PER-M",
      "http://qudt.org/vocab/unit/J-PER-T",
      "http://qudt.org/vocab/unit/S-M2-PER-MOL",
      "http://qudt.org/vocab/unit/MicroM",
      "http://qudt.org/vocab/unit/NanoS-PER-M",
      "http://qudt.org/vocab/unit/PA-SEC-PER-M3",
      "http://qudt.org/vocab/unit/MicroTORR",
      "http://qudt.org/vocab/unit/MilliA-PER-IN",
      "http://qudt.org/vocab/unit/SH",
      "http://qudt.org/vocab/unit/KiloJ-PER-MOL",
      "http://qudt.org/vocab/unit/FT_H2O",
      "http://qudt.org/vocab/unit/K-PA-PER-SEC",
      "http://qudt.org/vocab/unit/TON_Metric-PER-M3",
      "http://qudt.org/vocab/unit/V-A",
      "http://qudt.org/vocab/unit/C-PER-KiloGM",
      "http://qudt.org/vocab/unit/OZ-PER-IN3",
      "http://qudt.org/vocab/unit/W-PER-M2-K",
      "http://qudt.org/vocab/unit/LB-PER-GAL_US",
      "http://qudt.org/vocab/unit/NanoMOL-PER-MicroMOL",
      "http://qudt.org/vocab/unit/GI_UK-PER-SEC",
      "http://qudt.org/vocab/unit/DEG_R",
      "http://qudt.org/vocab/unit/PAB",
      "http://qudt.org/vocab/unit/PER-T-M",
      "http://qudt.org/vocab/unit/M3-PER-SEC",
      "http://qudt.org/vocab/unit/GI_US-PER-SEC",
      "http://qudt.org/vocab/unit/RT",
      "http://qudt.org/vocab/unit/M2-SEC-PER-RAD",
      "http://qudt.org/vocab/unit/PA",
      "http://qudt.org/vocab/unit/C2-M-PER-J",
      "http://qudt.org/vocab/unit/DWT",
      "http://qudt.org/vocab/unit/CAD",
      "http://qudt.org/vocab/unit/H_Stat",
      "http://qudt.org/vocab/unit/KiloA-PER-M2",
      "http://qudt.org/vocab/unit/MicroGM-PER-L-HR",
      "http://qudt.org/vocab/unit/N-SEC",
      "http://qudt.org/vocab/unit/S_Stat",
      "http://qudt.org/vocab/unit/DEG-PER-M",
      "http://qudt.org/vocab/unit/HectoL",
      "http://qudt.org/vocab/unit/PINT_US-PER-DAY",
      "http://qudt.org/vocab/unit/FT-LB_F-PER-SEC",
      "http://qudt.org/vocab/unit/TanzanianShilling",
      "http://qudt.org/vocab/unit/KiloMOL-PER-MIN",
      "http://qudt.org/vocab/unit/W-PER-FT2",
      "http://qudt.org/vocab/unit/TONNE-PER-DAY"
    ]
  }
}